{"59359": {"appearances": {"0": [70327, ""]}, "armor": 2784, "displayid": 70327, "dura": 100, "nsockets": 3, "reqlevel": 85, "reqskill": 202, "reqskillrank": 525, "sellprice": 171803, "slotbak": 1, "socket1": 1, "socket2": 6, "socket3": 6, "socketbonus": 4136, "sta": 512, "str": 301}, "52293": {"avgbuyout": 5759972, "sellprice": 37500, "sta": 81, "meta": {"2": 3}}, "57932": {"dodgertng": 112, "mastrtng": 112, "reqlevel": 85, "slotbak": 2, "sta": 252, "str": 168}, "67144": {"appearances": {"0": [91321, ""]}, "armor": 2570, "displayid": 91321, "dura": 100, "mastrtng": 179, "nsockets": 1, "parryrtng": 112, "reqlevel": 85, "sellprice": 186633, "slotbak": 3, "socket1": 4, "socketbonus": 4123, "sta": 380, "str": 253}, "52231": {"avgbuyout": 1606964, "mastrtng": 20, "sellprice": 37500, "sta": 30, "color": 4}, "60354": {"appearances": {"0": [79839, ""]}, "armor": 3426, "classes": 2, "displayid": 79839, "dura": 165, "itemset": 934, "mastrtng": 208, "nsockets": 2, "parryrtng": 168, "reqlevel": 85, "slotbak": 5, "socket1": 2, "socket2": 4, "socketbonus": 4134, "sta": 512, "str": 341}, "52221": {"avgbuyout": 1839988, "exprtng": 20, "sellprice": 37500, "sta": 30, "color": 3}, "55059": {"appearances": {"0": [76722, ""]}, "armor": 1927, "displayid": 76722, "dodgertng": 169, "dura": 55, "mastrtng": 149, "nsockets": 1, "reqlevel": 85, "sellprice": 59222, "slotbak": 6, "socket1": 4, "socketbonus": 4155, "sta": 380, "str": 233}, "52269": {"mastrtng": 67, "reqskill": 755, "reqskillrank": 500, "sellprice": 11250, "color": 2}, "58102": {"appearances": {"0": [82124, ""]}, "armor": 2886, "displayid": 82124, "dmgrange": 0.2, "dodgertng": 262, "dura": 100, "hitrtng": 133, "nsockets": 2, "reqlevel": 85, "slotbak": 7, "socket1": 3, "socket2": 4, "socketbonus": 4134, "sta": 454, "str": 210}, "52219": {"avgbuyout": 702667, "mastrtng": 40, "sellprice": 37500, "color": 2}, "65051": {"appearances": {"0": [81291, ""]}, "armor": 2447, "displayid": 81291, "dodgertng": 185, "dura": 75, "mastrtng": 147, "nsockets": 1, "reqlevel": 85, "sellprice": 189008, "slotbak": 8, "socket1": 3, "socketbonus": 4154, "sta": 429, "str": 286}, "57870": {"appearances": {"0": [76386, ""]}, "armor": 1443, "displayid": 76386, "dura": 45, "hitrtng": 92, "mastrtng": 112, "nsockets": 1, "reqlevel": 85, "sellprice": 89969, "slotbak": 9, "socket1": 3, "socketbonus": 4123, "sta": 252, "str": 148}, "52163": {"avgbuyout": 310000, "mastrtng": 35, "sellprice": 9000, "color": 2}, "56428": {"appearances": {"0": [87532, ""]}, "armor": 2061, "displayid": 87532, "dura": 45, "mastrtng": 140, "nsockets": 1, "parryrtng": 130, "reqlevel": 85, "sellprice": 83450, "slotbak": 10, "socket1": 2, "socketbonus": 4123, "sta": 337, "str": 215}, "62440": {"buyprice": 213737, "exprtng": 98, "mastrtng": 168, "reqfaction": 1173, "reqlevel": 85, "reqrep": 6, "sellprice": 53434, "slotbak": 11, "sta": 252, "str": 120}, "56444": {"hitrtng": 85, "mastrtng": 168, "reqlevel": 85, "sellprice": 53434, "slotbak": 11, "sta": 252, "str": 128}, "62383": {"appearances": {"0": [84229, ""]}, "armor": 625, "buyprice": 530134, "displayid": 84229, "dodgertng": 127, "mastrtng": 127, "reqfaction": 1158, "reqlevel": 85, "reqrep": 7, "sellprice": 106026, "slotbak": 16, "sta": 286, "str": 190}, "65036": {"appearances": {"0": [71110, ""]}, "displayid": 71110, "dmgmax1": 1764, "dmgmin1": 949, "dmgrange": 0.6, "dmgtype1": 0, "dps": 521.73, "dura": 105, "mastrtng": 110, "mledmgmax": 1764, "mledmgmin": 949, "mledps": 521.73, "mlespeed": 2.6, "parryrtng": 110, "reqlevel": 85, "sellprice": 367279, "sheathtype": 3, "slotbak": 13, "speed": 2.6, "sta": 248, "str": 165}, "69764": {"appearances": {"0": [23835, ""]}, "armor": 11896, "displayid": 23835, "dodgertng": 114, "dura": 120, "mastrtng": 134, "reqlevel": 85, "sheathtype": 4, "slotbak": 14, "sta": 286, "str": 190}, "56337": {"dodgertng": 67, "mastrtng": 57, "nsockets": 1, "reqlevel": 85, "sellprice": 73635, "slotbak": 28, "socket1": 7, "sta": 143, "str": 95}, "68779": {"avgbuyout": 2876195, "sellprice": 37500, "str": 54, "meta": {"0": 3}}, "56411": {"dodgertng": 168, "exprtng": 85, "reqlevel": 85, "sellprice": 53434, "slotbak": 2, "sta": 252, "str": 128}, "58100": {"appearances": {"0": [85988, ""]}, "armor": 2474, "displayid": 85988, "dura": 80, "exprtng": 161, "hitrtng": 111, "nsockets": 1, "reqlevel": 85, "slotbak": 3, "socket1": 2, "socketbonus": 4163, "sta": 337, "str": 205}, "52242": {"avgbuyout": 510000, "sellprice": 37500, "sta": 60, "color": 1}, "58101": {"appearances": {"0": [82122, ""]}, "armor": 3298, "displayid": 82122, "dodgertng": 162, "dura": 135, "mastrtng": 182, "nsockets": 2, "reqlevel": 85, "slotbak": 5, "socket1": 3, "socket2": 4, "socketbonus": 4156, "sta": 454, "str": 282}, "56392": {"appearances": {"0": [76389, ""]}, "armor": 1855, "displayid": 76389, "dodgertng": 185, "dura": 45, "exprtng": 114, "nsockets": 1, "reqlevel": 85, "sellprice": 84763, "slotbak": 6, "socket1": 2, "socketbonus": 4154, "sta": 337, "str": 171}, "56283": {"appearances": {"0": [76393, ""]}, "armor": 2886, "displayid": 76393, "dmgrange": 0.2, "dura": 100, "exprtng": 133, "nsockets": 2, "parryrtng": 262, "reqlevel": 85, "sellprice": 171120, "slotbak": 7, "socket1": 3, "socket2": 2, "socketbonus": 4134, "sta": 454, "str": 210}, "56381": {"appearances": {"0": [76382, ""]}, "armor": 2268, "critstrkrtng": 141, "displayid": 76382, "dura": 65, "hitrtng": 131, "nsockets": 1, "reqlevel": 85, "sellprice": 130492, "slotbak": 8, "socket1": 4, "socketbonus": 4131, "sta": 337, "str": 205}, "52255": {"reqskill": 755, "reqskillrank": 500, "sellprice": 11250, "str": 67, "color": 0}, "62449": {"appearances": {"0": [76712, ""]}, "armor": 1499, "buyprice": 590650, "displayid": 76712, "dodgertng": 190, "dura": 55, "exprtng": 111, "reqfaction": 1173, "reqlevel": 85, "reqrep": 7, "sellprice": 118130, "slotbak": 9, "sta": 286, "str": 136}, "56270": {"dodgertng": 167, "hitrtng": 86, "reqlevel": 85, "sellprice": 53434, "slotbak": 11, "sta": 253, "str": 128}, "56398": {"mastrtng": 113, "parryrtng": 113, "reqlevel": 85, "sellprice": 53434, "slotbak": 11, "sta": 252, "str": 168}, "56369": {"appearances": {"0": [83205, ""]}, "armor": 580, "displayid": 83205, "mastrtng": 120, "parryrtng": 98, "reqlevel": 85, "sellprice": 71428, "slotbak": 16, "sta": 252, "str": 168}, "56342": {"appearances": {"0": [82272, ""]}, "displayid": 82272, "dmgmax1": 2518, "dmgmin1": 1678, "dmgrange": 0.4, "dmgtype1": 0, "dps": 552.11, "dura": 100, "hastertng": 202, "mastrtng": 202, "mledmgmax": 2518, "mledmgmin": 1678, "mledps": 552.11, "mlespeed": 3.8, "reqlevel": 85, "sellprice": 312532, "sheathtype": 1, "slotbak": 17, "speed": 3.8, "sta": 454, "str": 302}, "64819": {"buyprice": 366244, "classes": 34, "critstrkrtng": 67, "nsockets": 1, "reqlevel": 85, "resirtng": 67, "sellprice": 73248, "slotbak": 28, "socket1": 7, "sta": 151, "str": 100}, "52294": {"avgbuyout": 5559946, "sellprice": 37500, "sta": 81, "meta": {"1": 2}}, "56319": {"mastrtng": 120, "parryrtng": 98, "reqlevel": 85, "sellprice": 53434, "slotbak": 2, "sta": 252, "str": 168}, "58104": {"appearances": {"0": [74903, ""]}, "armor": 2474, "displayid": 74903, "dodgertng": 205, "dura": 80, "hitrtng": 111, "nsockets": 1, "reqlevel": 85, "slotbak": 3, "socket1": 2, "socketbonus": 4155, "sta": 337, "str": 161}, "60349": {"appearances": {"0": [81303, ""]}, "armor": 3426, "classes": 32, "displayid": 81303, "dura": 165, "itemset": 926, "mastrtng": 208, "nsockets": 2, "parryrtng": 168, "reqlevel": 85, "slotbak": 5, "socket1": 2, "socket2": 4, "socketbonus": 4134, "sta": 512, "str": 341}, "52240": {"avgbuyout": 1799997, "mastrtng": 20, "sellprice": 37500, "str": 20, "color": 5}, "52261": {"reqskill": 755, "reqskillrank": 500, "sellprice": 11250, "sta": 101, "color": 1}, "62384": {"appearances": {"0": [81299, ""]}, "armor": 1927, "buyprice": 624260, "critstrkrtng": 149, "displayid": 81299, "dura": 55, "mastrtng": 169, "nsockets": 1, "reqfaction": 1158, "reqlevel": 85, "reqrep": 7, "sellprice": 124852, "slotbak": 6, "socket1": 4, "socketbonus": 4135, "sta": 380, "str": 233}, "65070": {"dodgertng": 215, "exprtng": 126, "reqlevel": 85, "sellprice": 53434, "slotbak": 11, "sta": 322, "str": 153}, "62243": {"avgbuyout": 34900000, "hitrtng": 63, "mastrtng": 63, "nsockets": 1, "reqlevel": 85, "sellprice": 72852, "slotbak": 28, "socket1": 7, "sta": 143, "str": 95}, "57930": {"critstrkrtng": 112, "exprtng": 112, "reqlevel": 85, "slotbak": 2, "sta": 252, "str": 168}, "56452": {"appearances": {"0": [76749, ""]}, "armor": 2474, "displayid": 76749, "dodgertng": 130, "dura": 80, "mastrtng": 130, "nsockets": 1, "reqlevel": 85, "sellprice": 129580, "slotbak": 3, "socket1": 4, "socketbonus": 4155, "sta": 337, "str": 225}, "56308": {"appearances": {"0": [76391, ""]}, "armor": 3298, "displayid": 76391, "dura": 135, "mastrtng": 162, "nsockets": 2, "parryrtng": 182, "reqlevel": 85, "sellprice": 178898, "slotbak": 5, "socket1": 2, "socket2": 4, "socketbonus": 4139, "sta": 454, "str": 282}, "52206": {"avgbuyout": 1929867, "sellprice": 37500, "str": 40, "color": 0}, "56367": {"appearances": {"0": [76385, ""]}, "armor": 2886, "critstrkrtng": 167, "displayid": 76385, "dura": 100, "mastrtng": 185, "nsockets": 2, "reqlevel": 85, "sellprice": 165379, "slotbak": 7, "socket1": 2, "socket2": 4, "socketbonus": 4137, "sta": 454, "str": 262}, "62382": {"appearances": {"0": [95795, ""]}, "armor": 2268, "buyprice": 667767, "critstrkrtng": 150, "displayid": 95795, "dura": 65, "hastertng": 130, "nsockets": 1, "reqfaction": 1158, "reqlevel": 85, "reqrep": 6, "sellprice": 133553, "slotbak": 8, "socket1": 3, "socketbonus": 4135, "sta": 337, "str": 205}, "64684": {"appearances": {"0": [70449, ""]}, "armor": 1469, "buyprice": 426479, "classes": 35, "displayid": 70449, "dura": 45, "exprtng": 119, "reqlevel": 85, "resirtng": 119, "sellprice": 85295, "slotbak": 9, "sta": 267, "str": 178}, "58099": {"appearances": {"0": [92257, ""]}, "armor": 2061, "critstrkrtng": 111, "displayid": 92257, "dura": 45, "mastrtng": 161, "nsockets": 1, "reqlevel": 85, "slotbak": 10, "socket1": 4, "socketbonus": 4135, "sta": 337, "str": 205}, "56111": {"avgbuyout": 789999, "dodgertng": 100, "mastrtng": 100, "reqlevel": 83, "sellprice": 53434, "slotbak": 11, "sta": 224, "str": 149}, "63467": {"appearances": {"0": [27721, "inv_misc_cape_10"]}, "armor": 580, "critstrkrtng": 112, "displayid": 27721, "hastertng": 112, "reqlevel": 85, "sellprice": 73136, "slotbak": 16, "sta": 252, "str": 168}, "56460": {"appearances": {"0": [76496, ""]}, "armor": 942, "critstrkrtng": 162, "displayid": 76496, "dura": 80, "hastertng": 182, "int": 242, "nsockets": 2, "reqlevel": 85, "sellprice": 76379, "slotbak": 1, "socket1": 1, "socket2": 4, "socketbonus": 4150, "sta": 454}, "57934": {"int": 168, "mastrtng": 112, "reqlevel": 85, "slotbak": 2, "spi": 112, "sta": 252}, "58162": {"appearances": {"0": [74927, ""]}, "armor": 870, "critstrkrtng": 130, "displayid": 74927, "dmgrange": 0.2, "dura": 80, "int": 205, "nsockets": 1, "reqlevel": 85, "slotbak": 3, "socket1": 4, "socketbonus": 4143, "spi": 150, "sta": 337}, "60259": {"appearances": {"0": [92243, ""]}, "armor": 1251, "classes": 16, "critstrkrtng": 218, "displayid": 92243, "dura": 165, "int": 301, "itemset": 935, "nsockets": 2, "reqlevel": 85, "slotbak": 20, "socket1": 2, "socket2": 3, "socketbonus": 4129, "spi": 198, "sta": 512}, "62386": {"appearances": {"0": [78765, ""]}, "armor": 704, "buyprice": 357235, "displayid": 78765, "dura": 55, "int": 233, "mastrtng": 149, "nsockets": 1, "reqfaction": 1158, "reqlevel": 85, "reqrep": 7, "sellprice": 71447, "slotbak": 6, "socket1": 4, "socketbonus": 4143, "spi": 169, "sta": 380}, "56413": {"appearances": {"0": [76482, ""]}, "armor": 1015, "critstrkrtng": 172, "displayid": 76482, "dmgrange": 0.2, "dura": 100, "int": 262, "mastrtng": 192, "nsockets": 2, "reqlevel": 85, "sellprice": 96669, "slotbak": 7, "socket1": 2, "socket2": 4, "socketbonus": 4137, "sta": 454}, "66937": {"appearances": {"0": [76486, ""]}, "armor": 787, "critstrkrtng": 116, "displayid": 76486, "dura": 65, "hitrtng": 142, "int": 199, "sellprice": 74242, "slotbak": 8, "sta": 298}, "56453": {"appearances": {"0": [76500, ""]}, "armor": 507, "critstrkrtng": 112, "displayid": 76500, "dura": 45, "int": 168, "reqlevel": 85, "sellprice": 49637, "slotbak": 9, "spi": 112, "sta": 252}, "58158": {"appearances": {"0": [71220, ""]}, "armor": 725, "displayid": 71220, "dura": 45, "hastertng": 150, "int": 205, "mastrtng": 130, "nsockets": 1, "reqlevel": 85, "slotbak": 10, "socket1": 3, "socketbonus": 4143, "sta": 337}, "56418": {"critstrkrtng": 98, "int": 168, "reqlevel": 85, "sellprice": 53434, "slotbak": 11, "spi": 120, "sta": 252}, "62352": {"buyprice": 213737, "critstrkrtng": 112, "hastertng": 112, "int": 168, "reqfaction": 1171, "reqlevel": 85, "reqrep": 6, "sellprice": 53434, "slotbak": 11, "sta": 252}, "63448": {"appearances": {"0": [83955, ""]}, "armor": 580, "critstrkrtng": 112, "displayid": 83955, "int": 168, "reqlevel": 85, "sellprice": 73419, "slotbak": 16, "spi": 112, "sta": 252}, "56441": {"appearances": {"0": [76991, ""]}, "critstrkrtng": 91, "displayid": 76991, "dmgmax1": 958, "dmgmin1": 516, "dmgrange": 0.6, "dmgtype1": 0, "dps": 409.44, "dura": 65, "hitrtng": 78, "int": 129, "mledmgmax": 958, "mledmgmin": 516, "mledps": 409.44, "mlespeed": 1.8, "reqlevel": 85, "sellprice": 255544, "sheathtype": 3, "slotbak": 21, "speed": 1.8, "spldmg": 1729, "splheal": 1729, "sta": 194}, "57924": {"appearances": {"0": [82747, ""]}, "displayid": 82747, "hastertng": 112, "int": 168, "reqlevel": 85, "slotbak": 23, "spi": 112, "sta": 252}, "56296": {"appearances": {"0": [76994, ""]}, "displayid": 76994, "dmgrange": 0.6, "dps": 780.28, "dura": 65, "hitrtng": 56, "int": 95, "mastrtng": 68, "reqlevel": 85, "sellprice": 178515, "slotbak": 26, "speed": 1.8, "sta": 143}, "59448": {"appearances": {"0": [65425, ""]}, "armor": 2784, "displayid": 65425, "dura": 100, "int": 301, "nsockets": 3, "reqlevel": 85, "reqskill": 202, "reqskillrank": 525, "sellprice": 182421, "slotbak": 1, "socket1": 1, "socket2": 6, "socket3": 6, "socketbonus": 4149, "sta": 512}, "52296": {"avgbuyout": 4500000, "int": 54, "sellprice": 37500, "meta": {"1": 2}}, "65134": {"critstrkrtng": 143, "int": 215, "reqlevel": 85, "sellprice": 53434, "slotbak": 2, "spi": 143, "sta": 322}, "62434": {"buyprice": 213737, "critstrkrtng": 127, "int": 190, "mastrtng": 127, "reqfaction": 1174, "reqlevel": 85, "reqrep": 7, "sellprice": 53434, "slotbak": 2, "sta": 286}, "65067": {"appearances": {"0": [91385, ""]}, "armor": 2669, "displayid": 91385, "dmgrange": 0.2, "dura": 100, "int": 266, "mastrtng": 171, "nsockets": 1, "reqlevel": 85, "sellprice": 186250, "slotbak": 3, "socket1": 4, "socketbonus": 4143, "spi": 191, "sta": 429}, "52236": {"avgbuyout": 1250000, "int": 20, "sellprice": 37500, "spi": 20, "color": 3}, "65042": {"appearances": {"0": [81974, ""]}, "armor": 3559, "displayid": 81974, "dura": 165, "hastertng": 247, "int": 345, "nsockets": 2, "reqlevel": 85, "sellprice": 237659, "slotbak": 5, "socket1": 2, "socket2": 4, "socketbonus": 4140, "spi": 227, "sta": 578}, "52208": {"avgbuyout": 984770, "int": 20, "mlehastertng": 20, "rgdhastertng": 20, "sellprice": 37500, "splhastertng": 20, "color": 5}, "62448": {"appearances": {"0": [79828, ""]}, "armor": 1927, "buyprice": 588414, "displayid": 79828, "dura": 55, "hastertng": 149, "int": 233, "nsockets": 1, "reqfaction": 1173, "reqlevel": 85, "reqrep": 7, "sellprice": 117682, "slotbak": 6, "socket1": 2, "socketbonus": 4142, "spi": 169, "sta": 380}, "52207": {"avgbuyout": 1907990, "int": 40, "sellprice": 37500, "color": 0}, "58107": {"appearances": {"0": [95791, ""]}, "armor": 2886, "displayid": 95791, "dura": 100, "int": 262, "mastrtng": 172, "nsockets": 2, "reqlevel": 85, "slotbak": 7, "socket1": 3, "socket2": 4, "socketbonus": 4129, "spi": 192, "sta": 454}, "63483": {"appearances": {"0": [75437, ""]}, "armor": 2268, "displayid": 75437, "dura": 65, "int": 205, "mastrtng": 150, "nsockets": 1, "reqlevel": 85, "sellprice": 125803, "slotbak": 8, "socket1": 2, "socketbonus": 4123, "spi": 130, "sta": 337}, "56464": {"appearances": {"0": [75065, ""]}, "armor": 1443, "displayid": 75065, "dura": 45, "int": 168, "mastrtng": 112, "reqlevel": 85, "sellprice": 84456, "slotbak": 9, "spi": 112, "sta": 252}, "62365": {"appearances": {"0": [79840, ""]}, "armor": 2141, "buyprice": 626557, "critstrkrtng": 149, "displayid": 79840, "dura": 55, "int": 233, "nsockets": 1, "reqfaction": 1135, "reqlevel": 85, "reqrep": 7, "sellprice": 125311, "slotbak": 10, "socket1": 2, "socketbonus": 4142, "spi": 169, "sta": 380}, "56373": {"critstrkrtng": 112, "int": 168, "reqlevel": 85, "sellprice": 53434, "slotbak": 11, "spi": 112, "sta": 252}, "64904": {"hastertng": 127, "int": 190, "mastrtng": 127, "reqlevel": 85, "slotbak": 11, "sta": 286}, "62357": {"appearances": {"0": [83351, "inv_misc_cape_cataclysm_caster_b_01"]}, "armor": 580, "buyprice": 365606, "critstrkrtng": 112, "displayid": 83351, "hastertng": 112, "int": 168, "reqfaction": 1135, "reqlevel": 85, "reqrep": 6, "sellprice": 73121, "slotbak": 16, "sta": 252}, "57872": {"appearances": {"0": [76979, ""]}, "displayid": 76979, "dmgmax1": 1225, "dmgmin1": 659, "dmgrange": 0.6, "dmgtype1": 0, "dps": 409.57, "dura": 90, "hastertng": 86, "int": 129, "mledmgmax": 1225, "mledmgmin": 659, "mledps": 409.57, "mlespeed": 2.3, "reqlevel": 85, "sellprice": 257433, "sheathtype": 3, "slotbak": 21, "speed": 2.3, "spi": 86, "spldmg": 1729, "splheal": 1729, "sta": 194}, "55070": {"appearances": {"0": [75548, ""]}, "armor": 11896, "avgbuyout": 89400000, "displayid": 75548, "dura": 120, "hastertng": 112, "int": 170, "nsockets": 1, "reqlevel": 85, "sellprice": 115029, "sheathtype": 4, "slotbak": 14, "socket1": 4, "socketbonus": 4143, "spi": 122, "sta": 286}, "56372": {"hastertng": 69, "int": 95, "nsockets": 1, "reqlevel": 85, "sellprice": 72248, "slotbak": 28, "socket1": 7, "spi": 54, "sta": 143}, "59458": {"appearances": {"0": [65425, ""]}, "armor": 1977, "displayid": 65425, "dura": 100, "int": 301, "nsockets": 3, "reqlevel": 85, "reqskill": 202, "reqskillrank": 525, "sellprice": 150956, "slotbak": 1, "socket1": 1, "socket2": 6, "socket3": 6, "socketbonus": 4149, "sta": 512}, "68780": {"avgbuyout": 3059937, "int": 54, "sellprice": 37500, "meta": {"0": 3}}, "56300": {"hastertng": 98, "int": 168, "reqlevel": 85, "sellprice": 53434, "slotbak": 2, "spi": 120, "sta": 252}, "63452": {"appearances": {"0": [76414, ""]}, "armor": 1741, "displayid": 76414, "dura": 80, "int": 205, "mastrtng": 130, "nsockets": 1, "reqlevel": 85, "sellprice": 112270, "slotbak": 3, "socket1": 2, "socketbonus": 4123, "spi": 150, "sta": 337}, "60309": {"appearances": {"0": [82049, ""]}, "armor": 2433, "classes": 64, "critstrkrtng": 188, "displayid": 82049, "dura": 165, "hastertng": 228, "int": 301, "itemset": 938, "nsockets": 2, "reqlevel": 85, "slotbak": 5, "socket1": 2, "socket2": 4, "socketbonus": 4149, "sta": 512}, "62445": {"appearances": {"0": [74914, ""]}, "armor": 1306, "buyprice": 358820, "displayid": 74914, "dura": 45, "hastertng": 130, "int": 205, "nsockets": 1, "reqfaction": 1173, "reqlevel": 85, "reqrep": 6, "sellprice": 71764, "slotbak": 6, "socket1": 3, "socketbonus": 4143, "spi": 150, "sta": 337}, "62380": {"appearances": {"0": [74915, ""]}, "armor": 2032, "buyprice": 759100, "displayid": 74915, "dura": 100, "hastertng": 172, "int": 262, "nsockets": 2, "reqfaction": 1158, "reqlevel": 85, "reqrep": 6, "sellprice": 151820, "slotbak": 7, "socket1": 2, "socket2": 3, "socketbonus": 4129, "spi": 192, "sta": 454}, "62363": {"appearances": {"0": [82048, ""]}, "armor": 1673, "buyprice": 798890, "critstrkrtng": 149, "displayid": 82048, "dura": 75, "int": 233, "nsockets": 1, "reqfaction": 1135, "reqlevel": 85, "reqrep": 7, "sellprice": 159778, "slotbak": 8, "socket1": 3, "socketbonus": 4142, "spi": 169, "sta": 380}, "63486": {"appearances": {"0": [76415, ""]}, "armor": 1016, "displayid": 76415, "dura": 45, "hastertng": 112, "int": 168, "reqlevel": 85, "sellprice": 72852, "slotbak": 9, "spi": 112, "sta": 252}, "58130": {"appearances": {"0": [74918, ""]}, "armor": 1451, "critstrkrtng": 150, "displayid": 74918, "dmgrange": 0.2, "dura": 45, "int": 205, "mastrtng": 130, "nsockets": 1, "reqlevel": 85, "slotbak": 10, "socket1": 3, "socketbonus": 4143, "sta": 337}, "56312": {"appearances": {"0": [77011, ""]}, "displayid": 77011, "dmgmax1": 1225, "dmgmin1": 659, "dmgrange": 0.6, "dmgtype1": 0, "dps": 409.57, "dura": 90, "int": 129, "mastrtng": 78, "mledmgmax": 1225, "mledmgmin": 659, "mledps": 409.57, "mlespeed": 2.3, "reqlevel": 85, "sellprice": 259222, "sheathtype": 3, "slotbak": 21, "speed": 2.3, "spi": 91, "spldmg": 1729, "splheal": 1729, "sta": 194}, "56289": {"appearances": {"0": [82634, ""]}, "critstrkrtng": 98, "displayid": 82634, "int": 168, "reqlevel": 85, "sellprice": 53434, "slotbak": 23, "spi": 120, "sta": 252}, "56350": {"classes": 1090, "critstrkrtng": 63, "int": 95, "nsockets": 1, "reqlevel": 85, "sellprice": 77200, "slotbak": 28, "socket1": 7, "spi": 63, "sta": 143}, "56563": {"appearances": {"0": [82041, ""]}, "armor": 2433, "critstrkrtng": 214, "displayid": 82041, "dura": 165, "hastertng": 216, "int": 321, "nsockets": 1, "reqlevel": 85, "sellprice": 101750, "slotbak": 5, "socket1": 2, "socketbonus": 4211, "sta": 512}, "56538": {"appearances": {"0": [82037, ""]}, "armor": 1369, "avgbuyout": 95009778, "critstrkrtng": 188, "displayid": 82037, "dura": 55, "int": 233, "mastrtng": 116, "nsockets": 1, "reqlevel": 85, "sellprice": 53729, "slotbak": 6, "socket1": 2, "socketbonus": 4143, "sta": 380}, "60310": {"appearances": {"0": [82051, ""]}, "armor": 2129, "classes": 64, "critstrkrtng": 198, "displayid": 82051, "dura": 120, "int": 301, "itemset": 938, "nsockets": 2, "reqlevel": 85, "slotbak": 7, "socket1": 3, "socket2": 4, "socketbonus": 4144, "spi": 218, "sta": 512}, "56524": {"appearances": {"0": [74917, ""]}, "armor": 993, "avgbuyout": 8499979, "displayid": 74917, "dura": 45, "hitrtng": 80, "int": 158, "reqlevel": 85, "resirtng": 120, "sellprice": 35274, "slotbak": 9, "sta": 237}, "65055": {"appearances": {"0": [81285, ""]}, "armor": 1593, "critstrkrtng": 191, "displayid": 81285, "dmgrange": 0.2, "dura": 55, "int": 266, "nsockets": 1, "reqlevel": 85, "sellprice": 109778, "slotbak": 10, "socket1": 2, "socketbonus": 4142, "spi": 171, "sta": 429}, "63475": {"appearances": {"0": [76411, ""]}, "armor": 1451, "displayid": 76411, "dmgrange": 0.2, "dura": 45, "hastertng": 130, "int": 205, "nsockets": 1, "reqlevel": 85, "sellprice": 77297, "slotbak": 10, "socket1": 3, "socketbonus": 4143, "spi": 150, "sta": 337}, "56269": {"appearances": {"0": [76505, ""]}, "armor": 942, "displayid": 76505, "dura": 80, "int": 242, "mastrtng": 176, "nsockets": 2, "reqlevel": 85, "sellprice": 74985, "slotbak": 1, "socket1": 1, "socket2": 4, "socketbonus": 4125, "spi": 157, "sta": 454}, "63465": {"appearances": {"0": [76506, ""]}, "armor": 870, "displayid": 76506, "dmgrange": 0.2, "dura": 80, "int": 205, "mastrtng": 150, "nsockets": 1, "reqlevel": 85, "sellprice": 72584, "slotbak": 3, "socket1": 3, "socketbonus": 4143, "spi": 130, "sta": 337}, "65079": {"appearances": {"0": [82119, ""]}, "armor": 757, "critstrkrtng": 171, "displayid": 82119, "dura": 55, "int": 266, "nsockets": 1, "reqlevel": 85, "sellprice": 68983, "slotbak": 6, "socket1": 3, "socketbonus": 4143, "spi": 191, "sta": 429}, "58160": {"appearances": {"0": [76551, ""]}, "armor": 1015, "displayid": 76551, "dmgrange": 0.2, "dura": 100, "hastertng": 147, "int": 262, "nsockets": 2, "reqlevel": 85, "slotbak": 7, "socket1": 2, "socket2": 4, "socketbonus": 4144, "spi": 206, "sta": 454}, "63440": {"appearances": {"0": [76501, ""]}, "armor": 797, "critstrkrtng": 130, "displayid": 76501, "dura": 65, "int": 205, "nsockets": 1, "reqlevel": 85, "sellprice": 71227, "slotbak": 8, "socket1": 3, "socketbonus": 4143, "spi": 150, "sta": 337}, "62364": {"appearances": {"0": [77130, ""]}, "armor": 782, "buyprice": 354762, "displayid": 77130, "dura": 55, "hastertng": 149, "int": 233, "mastrtng": 169, "nsockets": 1, "reqfaction": 1135, "reqlevel": 85, "reqrep": 7, "sellprice": 70952, "slotbak": 10, "socket1": 4, "socketbonus": 4143, "sta": 380}, "56391": {"int": 168, "mastrtng": 120, "reqlevel": 85, "sellprice": 53434, "slotbak": 11, "spi": 98, "sta": 252}, "56307": {"int": 168, "mastrtng": 98, "reqlevel": 85, "sellprice": 53434, "slotbak": 11, "spi": 120, "sta": 252}, "56424": {"appearances": {"0": [76995, ""]}, "displayid": 76995, "dmgmax1": 1590, "dmgmin1": 1060, "dmgrange": 0.4, "dmgtype1": 0, "dps": 552.08, "dura": 100, "hastertng": 202, "int": 302, "mledmgmax": 1590, "mledmgmin": 1060, "mledps": 552.08, "mlespeed": 2.4, "reqlevel": 85, "sellprice": 322878, "sheathtype": 2, "slotbak": 17, "speed": 2.4, "spi": 202, "spldmg": 1732, "splheal": 1732, "sta": 454}, "56446": {"appearances": {"0": [76982, ""]}, "displayid": 76982, "dmgrange": 0.6, "dps": 780.28, "dura": 65, "hastertng": 63, "int": 95, "reqlevel": 85, "sellprice": 195069, "slotbak": 26, "speed": 1.8, "spi": 63, "sta": 143}, "67147": {"appearances": {"0": [91255, ""]}, "armor": 1016, "displayid": 91255, "dura": 100, "hastertng": 185, "int": 281, "nsockets": 2, "reqlevel": 85, "sellprice": 107984, "slotbak": 1, "socket1": 1, "socket2": 2, "socketbonus": 4128, "spi": 201, "sta": 512}, "52144": {"avgbuyout": 719990, "int": 18, "mlehastertng": 17, "rgdhastertng": 17, "sellprice": 9000, "splhastertng": 17, "color": 5}, "58153": {"appearances": {"0": [76572, ""]}, "armor": 1160, "displayid": 76572, "dura": 135, "hastertng": 202, "int": 262, "mastrtng": 162, "nsockets": 2, "reqlevel": 85, "slotbak": 20, "socket1": 2, "socket2": 4, "socketbonus": 4137, "sta": 454}, "54505": {"appearances": {"0": [81995, ""]}, "armor": 1094, "critstrkrtng": 214, "displayid": 81995, "dmgrange": 0.2, "dura": 120, "hastertng": 216, "int": 321, "nsockets": 1, "reqlevel": 85, "sellprice": 71893, "slotbak": 7, "socket1": 2, "socketbonus": 4146, "sta": 512}, "68356": {"avgbuyout": 1455933, "int": 20, "resirtng": 20, "sellprice": 37500, "color": 5}, "63484": {"appearances": {"0": [76480, ""]}, "armor": 507, "critstrkrtng": 112, "displayid": 76480, "dura": 45, "int": 168, "mastrtng": 112, "reqlevel": 85, "sellprice": 48200, "slotbak": 9, "sta": 252}, "56333": {"critstrkrtng": 112, "hastertng": 112, "int": 168, "reqlevel": 85, "sellprice": 53434, "slotbak": 11, "sta": 252}, "56267": {"appearances": {"0": [83351, ""]}, "armor": 580, "displayid": 83351, "hastertng": 112, "int": 168, "mastrtng": 112, "reqlevel": 85, "sellprice": 74441, "slotbak": 16, "sta": 252}, "64880": {"appearances": {"0": [75026, ""]}, "critstrkrtng": 194, "displayid": 75026, "dmgmax1": 1795, "dmgmin1": 1196, "dmgrange": 0.4, "dmgtype1": 0, "dps": 623.13, "dura": 120, "int": 341, "mledmgmax": 1795, "mledmgmin": 1196, "mledps": 623.13, "mlespeed": 2.4, "reqlevel": 85, "sheathtype": 2, "slotbak": 17, "speed": 2.4, "spi": 247, "spldmg": 1955, "splheal": 1955, "sta": 512}, "58108": {"appearances": {"0": [95851, ""]}, "armor": 2680, "critstrkrtng": 172, "displayid": 95851, "dura": 80, "int": 242, "nsockets": 2, "reqlevel": 85, "slotbak": 1, "socket1": 1, "socket2": 4, "socketbonus": 2666, "spi": 172, "sta": 454}, "56272": {"appearances": {"0": [76748, ""]}, "armor": 2474, "displayid": 76748, "dmgrange": 0.2, "dura": 80, "hastertng": 150, "int": 205, "nsockets": 1, "reqlevel": 85, "sellprice": 135858, "slotbak": 3, "socket1": 2, "socketbonus": 4146, "spi": 130, "sta": 337}, "63464": {"appearances": {"0": [75063, ""]}, "armor": 2886, "displayid": 75063, "dura": 100, "hastertng": 202, "int": 262, "nsockets": 2, "reqlevel": 85, "sellprice": 168719, "slotbak": 7, "socket1": 2, "socket2": 4, "socketbonus": 4140, "spi": 162, "sta": 454}, "65080": {"appearances": {"0": [81975, ""]}, "armor": 2447, "displayid": 81975, "dura": 75, "int": 266, "mastrtng": 171, "nsockets": 1, "reqlevel": 85, "sellprice": 181426, "slotbak": 8, "socket1": 4, "socketbonus": 4143, "spi": 191, "sta": 429}, "63476": {"appearances": {"0": [75065, ""]}, "armor": 1443, "critstrkrtng": 112, "displayid": 75065, "dura": 45, "int": 168, "reqlevel": 85, "sellprice": 91018, "slotbak": 9, "spi": 112, "sta": 252}, "56434": {"appearances": {"0": [83955, ""]}, "armor": 580, "displayid": 83955, "hastertng": 112, "int": 168, "reqlevel": 85, "sellprice": 74739, "slotbak": 16, "spi": 112, "sta": 252}, "57925": {"appearances": {"0": [82879, ""]}, "armor": 11696, "displayid": 82879, "dura": 100, "int": 168, "mastrtng": 112, "reqlevel": 85, "sheathtype": 4, "slotbak": 14, "spi": 112, "sta": 252}, "59449": {"appearances": {"0": [65425, ""]}, "armor": 1016, "displayid": 65425, "dura": 100, "int": 301, "nsockets": 3, "reqlevel": 85, "reqskill": 202, "reqskillrank": 525, "sellprice": 104821, "slotbak": 1, "socket1": 1, "socket2": 6, "socket3": 6, "socketbonus": 4144, "sta": 512}, "56385": {"critstrkrtng": 112, "hastertng": 112, "int": 168, "reqlevel": 85, "sellprice": 53434, "slotbak": 2, "sta": 252}, "56399": {"appearances": {"0": [76481, ""]}, "armor": 870, "critstrkrtng": 150, "displayid": 76481, "dmgrange": 0.2, "dura": 80, "hastertng": 130, "int": 205, "nsockets": 1, "reqlevel": 85, "sellprice": 74157, "slotbak": 3, "socket1": 4, "socketbonus": 4143, "sta": 337}, "52217": {"avgbuyout": 1299994, "int": 20, "mlehitrtng": 20, "rgdhitrtng": 20, "sellprice": 37500, "splhitrtng": 20, "color": 3}, "60244": {"appearances": {"0": [93770, ""]}, "armor": 1251, "classes": 128, "critstrkrtng": 218, "displayid": 93770, "dura": 165, "hastertng": 198, "int": 301, "itemset": 931, "nsockets": 2, "reqlevel": 85, "slotbak": 20, "socket1": 2, "socket2": 4, "socketbonus": 4144, "sta": 512}, "54503": {"appearances": {"0": [77127, ""]}, "armor": 704, "avgbuyout": 93000000, "displayid": 77127, "dura": 55, "hitrtng": 149, "int": 233, "mastrtng": 169, "nsockets": 1, "reqlevel": 85, "sellprice": 35692, "slotbak": 6, "socket1": 4, "socketbonus": 4160, "sta": 380}, "58154": {"appearances": {"0": [71217, ""]}, "armor": 1015, "critstrkrtng": 162, "displayid": 71217, "dmgrange": 0.2, "dura": 100, "hastertng": 202, "int": 262, "nsockets": 2, "reqlevel": 85, "slotbak": 7, "socket1": 2, "socket2": 3, "socketbonus": 4140, "sta": 454}, "52239": {"avgbuyout": 1492986, "int": 20, "mlecritstrkrtng": 20, "rgdcritstrkrtng": 20, "sellprice": 37500, "splcritstrkrtng": 20, "color": 5}, "64723": {"appearances": {"0": [85473, ""]}, "armor": 526, "buyprice": 241332, "classes": 400, "displayid": 85473, "dura": 45, "hitrtng": 119, "int": 178, "reqlevel": 85, "resirtng": 119, "sellprice": 48266, "slotbak": 9, "sta": 267}, "56432": {"critstrkrtng": 112, "hitrtng": 112, "int": 168, "reqlevel": 85, "sellprice": 53434, "slotbak": 11, "sta": 252}, "65169": {"hitrtng": 107, "int": 133, "mastrtng": 112, "nsockets": 1, "reqlevel": 85, "sellprice": 12812, "slotbak": 11, "socket1": 2, "socketbonus": 4160, "sta": 252}, "56306": {"appearances": {"0": [82636, ""]}, "critstrkrtng": 98, "displayid": 82636, "hitrtng": 120, "int": 168, "reqlevel": 85, "sellprice": 53434, "slotbak": 23, "sta": 252}, "59456": {"agi": 301, "appearances": {"0": [71934, ""]}, "armor": 1977, "displayid": 71934, "dura": 100, "nsockets": 3, "reqlevel": 85, "reqskill": 202, "reqskillrank": 525, "sellprice": 149828, "slotbak": 1, "socket1": 1, "socket2": 6, "socket3": 6, "socketbonus": 4133, "sta": 512}, "68778": {"agi": 54, "avgbuyout": 2899997, "sellprice": 37500, "meta": {"0": 3}}, "52350": {"agi": 138, "avgbuyout": 79999950, "critstrkrtng": 112, "hastertng": 102, "nsockets": 1, "reqlevel": 85, "sellprice": 55086, "slotbak": 2, "socket1": 2, "socketbonus": 2782, "sta": 252}, "52212": {"agi": 40, "avgbuyout": 1939854, "sellprice": 37500, "color": 0}, "60427": {"agi": 248, "appearances": {"0": [84792, ""]}, "armor": 1864, "classes": 4, "displayid": 84792, "dmgrange": 0.2, "dura": 100, "hastertng": 159, "itemset": -328, "nsockets": 1, "reqlevel": 85, "resirtng": 179, "sellprice": 161103, "slotbak": 3, "socket1": 3, "socketbonus": 2782, "sta": 402}, "65037": {"agi": 345, "appearances": {"0": [81886, ""]}, "armor": 2548, "displayid": 81886, "dura": 165, "hitrtng": 257, "mastrtng": 217, "nsockets": 2, "reqlevel": 85, "sellprice": 221156, "slotbak": 5, "socket1": 2, "socket2": 4, "socketbonus": 4133, "sta": 578}, "52258": {"agi": 67, "reqskill": 755, "reqskillrank": 500, "sellprice": 11250, "color": 0}, "52220": {"agi": 20, "avgbuyout": 1309970, "mlehitrtng": 20, "rgdhitrtng": 20, "sellprice": 37500, "splhitrtng": 20, "color": 3}, "56539": {"agi": 233, "appearances": {"0": [79811, ""]}, "armor": 1369, "critstrkrtng": 159, "displayid": 79811, "dura": 55, "mastrtng": 159, "nsockets": 1, "reqlevel": 85, "sellprice": 53920, "slotbak": 6, "socket1": 2, "socketbonus": 2782, "sta": 380}, "56386": {"agi": 262, "appearances": {"0": [76420, ""]}, "armor": 2032, "critstrkrtng": 172, "displayid": 76420, "dura": 100, "hitrtng": 192, "nsockets": 2, "reqlevel": 85, "sellprice": 156115, "slotbak": 7, "socket1": 2, "socket2": 4, "socketbonus": 4152, "sta": 454}, "58199": {"agi": 233, "appearances": {"0": [81813, ""]}, "armor": 1673, "critstrkrtng": 149, "displayid": 81813, "dura": 75, "mastrtng": 169, "nsockets": 1, "reqlevel": 85, "slotbak": 8, "socket1": 2, "socketbonus": 4123, "sta": 380}, "63479": {"agi": 168, "appearances": {"0": [76416, ""]}, "armor": 1016, "critstrkrtng": 112, "displayid": 76416, "dura": 45, "hastertng": 112, "reqlevel": 85, "sellprice": 70928, "slotbak": 9, "sta": 252}, "60424": {"agi": 248, "appearances": {"0": [84789, ""]}, "armor": 1554, "classes": 4, "displayid": 84789, "dura": 55, "hitrtng": 159, "itemset": -328, "nsockets": 1, "reqlevel": 85, "resirtng": 179, "sellprice": 105775, "slotbak": 10, "socket1": 4, "socketbonus": 2782, "sta": 402}, "52348": {"agi": 148, "avgbuyout": 99999972, "critstrkrtng": 89, "mastrtng": 114, "nsockets": 1, "reqlevel": 85, "sellprice": 55086, "slotbak": 11, "socket1": 2, "socketbonus": 4211, "sta": 252}, "62362": {"agi": 190, "buyprice": 213737, "hastertng": 127, "mastrtng": 127, "reqfaction": 1135, "reqlevel": 85, "reqrep": 7, "sellprice": 53434, "slotbak": 11, "sta": 286}, "56315": {"agi": 168, "appearances": {"0": [83349, ""]}, "armor": 580, "critstrkrtng": 112, "displayid": 83349, "hastertng": 112, "reqlevel": 85, "sellprice": 71122, "slotbak": 16, "sta": 252}, "65168": {"agi": 302, "appearances": {"0": [19242, ""]}, "critstrkrtng": 182, "displayid": 19242, "dmgmax1": 2253, "dmgmin1": 1502, "dmgrange": 0.4, "dmgtype1": 0, "dps": 552.21, "dura": 100, "mastrtng": 213, "mledmgmax": 2253, "mledmgmin": 1502, "mledps": 552.21, "mlespeed": 3.4, "reqlevel": 85, "sellprice": 319802, "sheathtype": 1, "slotbak": 17, "speed": 3.4, "sta": 454}, "63532": {"agi": 107, "appearances": {"0": [68047, "inv_weapon_crossbow_02"]}, "critstrkrtng": 72, "displayid": 68047, "dmgmax1": 2244, "dmgmin1": 1496, "dmgrange": 0.4, "dmgtype1": 2, "dps": 623.33, "dura": 90, "hastertng": 72, "reqlevel": 85, "rgddmgmax": 2244, "rgddmgmin": 1496, "rgddps": 623.33, "rgdspeed": 3.0, "sellprice": 264088, "slotbak": 26, "speed": 3.0, "sta": 161}, "59367": {"agi": 75, "appearances": {"0": [70338, ""]}, "avgbuyout": 95000658, "critstrkrtng": 65, "displayid": 70338, "dmgmax1": 2010, "dmgmin1": 1082, "dmgrange": 0.6, "dmgtype1": 0, "dps": 552.14, "dura": 75, "hastertng": 42, "nsockets": 1, "reqlevel": 85, "rgddmgmax": 2010, "rgddmgmin": 1082, "rgddps": 552.14, "rgdspeed": 2.8, "sellprice": 183418, "slotbak": 26, "socket1": 2, "socketbonus": 2782, "speed": 2.8, "sta": 143}, "62450": {"appearances": {"0": [82067, ""]}, "armor": 860, "buyprice": 505301, "displayid": 82067, "dura": 75, "hastertng": 149, "hitrtng": 169, "int": 233, "nsockets": 1, "reqfaction": 1173, "reqlevel": 85, "reqrep": 7, "sellprice": 101060, "slotbak": 8, "socket1": 3, "socketbonus": 4160, "sta": 380}, "56389": {"appearances": {"0": [76480, ""]}, "armor": 507, "critstrkrtng": 112, "displayid": 76480, "dura": 45, "hitrtng": 112, "int": 168, "reqlevel": 85, "sellprice": 47609, "slotbak": 9, "sta": 252}, "64489": {"appearances": {"0": [75035, ""]}, "critstrkrtng": 228, "displayid": 75035, "dmgmax1": 1571, "dmgmin1": 1047, "dmgrange": 0.4, "dmgtype1": 0, "dps": 623.33, "dura": 120, "hastertng": 228, "int": 341, "mledmgmax": 1571, "mledmgmin": 1047, "mledps": 623.33, "mlespeed": 2.1, "reqlevel": 85, "sheathtype": 2, "slotbak": 17, "speed": 2.1, "spldmg": 1955, "splheal": 1955, "sta": 512}, "55823": {"appearances": {"0": [76983, ""]}, "avgbuyout": 389932, "critstrkrtng": 48, "displayid": 76983, "dmgrange": 0.6, "dps": 590.0, "dura": 65, "hastertng": 48, "int": 72, "reqlevel": 81, "sellprice": 162939, "slotbak": 26, "speed": 1.8, "sta": 108}, "62447": {"buyprice": 213737, "critstrkrtng": 127, "hastertng": 127, "reqfaction": 1173, "reqlevel": 85, "reqrep": 7, "sellprice": 53434, "slotbak": 2, "sta": 286, "str": 190}, "60412": {"appearances": {"0": [86082, ""]}, "armor": 2615, "classes": 32, "displayid": 86082, "dura": 100, "exprtng": 159, "itemset": -332, "nsockets": 1, "reqlevel": 85, "resirtng": 179, "sellprice": 190149, "slotbak": 3, "socket1": 3, "socketbonus": 4135, "sta": 402, "str": 248}, "52214": {"avgbuyout": 860570, "mlehastertng": 20, "rgdhastertng": 20, "sellprice": 37500, "splhastertng": 20, "str": 20, "color": 5}, "55060": {"appearances": {"0": [76718, ""]}, "armor": 3426, "critstrkrtng": 228, "displayid": 76718, "dmgrange": 0.6, "dura": 165, "mastrtng": 208, "nsockets": 1, "reqlevel": 85, "sellprice": 118204, "sheathtype": 3, "slotbak": 5, "socket1": 3, "socketbonus": 4135, "speed": 2.6, "sta": 512, "str": 321}, "55061": {"appearances": {"0": [76722, ""]}, "armor": 1927, "avgbuyout": 94949997, "displayid": 76722, "dura": 55, "hastertng": 149, "hitrtng": 169, "nsockets": 1, "reqlevel": 85, "sellprice": 59663, "slotbak": 6, "socket1": 3, "socketbonus": 4135, "sta": 380, "str": 233}, "58097": {"appearances": {"0": [92259, ""]}, "armor": 2886, "critstrkrtng": 182, "displayid": 92259, "dura": 100, "hastertng": 182, "nsockets": 2, "reqlevel": 85, "slotbak": 7, "socket1": 3, "socket2": 4, "socketbonus": 4136, "sta": 454, "str": 262}, "56301": {"appearances": {"0": [76386, ""]}, "armor": 1443, "critstrkrtng": 112, "displayid": 76386, "dura": 45, "exprtng": 112, "reqlevel": 85, "sellprice": 85393, "slotbak": 9, "sta": 252, "str": 168}, "60409": {"appearances": {"0": [86075, ""]}, "armor": 2179, "classes": 32, "displayid": 86075, "dura": 55, "hitrtng": 159, "itemset": -332, "nsockets": 1, "reqlevel": 85, "resirtng": 179, "sellprice": 126382, "slotbak": 10, "socket1": 4, "socketbonus": 4135, "sta": 402, "str": 248}, "52213": {"avgbuyout": 1449997, "mlehitrtng": 20, "rgdhitrtng": 20, "sellprice": 37500, "splhitrtng": 20, "str": 20, "color": 3}, "56457": {"hastertng": 112, "hitrtng": 112, "reqlevel": 85, "sellprice": 53434, "slotbak": 11, "sta": 252, "str": 168}, "62350": {"buyprice": 213737, "critstrkrtng": 112, "hastertng": 112, "reqfaction": 1171, "reqlevel": 85, "reqrep": 6, "sellprice": 53434, "slotbak": 11, "sta": 252, "str": 168}, "56275": {"appearances": {"0": [83205, ""]}, "armor": 580, "displayid": 83205, "hastertng": 112, "mastrtng": 112, "reqlevel": 85, "sellprice": 71145, "slotbak": 16, "sta": 252, "str": 168}, "64377": {"appearances": {"0": [32603, "inv_sword_55"]}, "critstrkrtng": 238, "displayid": 32603, "dmgmax1": 2842, "dmgmin1": 1894, "dmgrange": 0.4, "dmgtype1": 0, "dps": 623.16, "dura": 120, "hitrtng": 216, "maxcount": 1, "mledmgmax": 2842, "mledmgmin": 1894, "mledps": 623.16, "mlespeed": 3.8, "reqlevel": 85, "sheathtype": 1, "slotbak": 17, "speed": 3.8, "sta": 512, "str": 341}, "64674": {"critstrkrtng": 72, "exprtng": 72, "nsockets": 1, "reqlevel": 85, "slotbak": 28, "socket1": 7, "sta": 161, "str": 107}, "56360": {"critstrkrtng": 112, "mastrtng": 112, "reqlevel": 85, "sellprice": 53434, "slotbak": 2, "sta": 252, "str": 168}, "58096": {"appearances": {"0": [92255, ""]}, "armor": 3298, "critstrkrtng": 192, "displayid": 92255, "dura": 135, "hitrtng": 172, "nsockets": 2, "reqlevel": 85, "slotbak": 5, "socket1": 2, "socket2": 4, "socketbonus": 4130, "sta": 454, "str": 262}, "65040": {"appearances": {"0": [81290, ""]}, "armor": 2002, "critstrkrtng": 191, "displayid": 81290, "dura": 55, "hitrtng": 171, "nsockets": 1, "reqlevel": 85, "sellprice": 131121, "slotbak": 6, "socket1": 2, "socketbonus": 4160, "sta": 429, "str": 266}, "65267": {"appearances": {"0": [82101, ""]}, "armor": 3114, "classes": 1, "displayid": 82101, "dura": 120, "hitrtng": 217, "itemset": -299, "mastrtng": 257, "nsockets": 2, "reqlevel": 85, "slotbak": 7, "socket1": 3, "socket2": 3, "socketbonus": 4140, "sta": 578, "str": 345}, "65085": {"appearances": {"0": [78789, ""]}, "armor": 1557, "displayid": 78789, "dura": 55, "hastertng": 143, "hitrtng": 143, "reqlevel": 85, "sellprice": 124176, "slotbak": 9, "sta": 322, "str": 215}, "56365": {"critstrkrtng": 120, "exprtng": 98, "reqlevel": 85, "sellprice": 53434, "slotbak": 11, "sta": 252, "str": 168}, "63739": {"appearances": {"0": [69421, ""]}, "displayid": 69421, "dmgmax1": 1549, "dmgmin1": 833, "dmgrange": 0.6, "dmgtype1": 0, "dps": 425.36, "dura": 65, "hitrtng": 39, "mastrtng": 54, "rgddmgmax": 1549, "rgddmgmin": 833, "rgddps": 425.36, "rgdspeed": 2.8, "sellprice": 147336, "slotbak": 26, "speed": 2.8, "sta": 110, "str": 73}, "59455": {"agi": 301, "appearances": {"0": [71934, ""]}, "armor": 1356, "displayid": 71934, "dura": 100, "nsockets": 3, "reqlevel": 85, "reqskill": 202, "reqskillrank": 525, "sellprice": 124380, "slotbak": 1, "socket1": 1, "socket2": 6, "socket3": 6, "socketbonus": 4133, "sta": 512}, "62378": {"agi": 168, "buyprice": 213737, "hastertng": 107, "mastrtng": 116, "reqfaction": 1158, "reqlevel": 85, "reqrep": 6, "sellprice": 53434, "slotbak": 2, "sta": 252}, "65083": {"agi": 266, "appearances": {"0": [76666, ""]}, "armor": 1328, "critstrkrtng": 171, "displayid": 76666, "dura": 100, "mastrtng": 191, "nsockets": 1, "reqlevel": 85, "sellprice": 131303, "slotbak": 3, "socket1": 2, "socketbonus": 4123, "sta": 429}, "63468": {"agi": 262, "appearances": {"0": [76442, ""]}, "armor": 1571, "displayid": 76442, "dura": 135, "hastertng": 182, "mastrtng": 182, "nsockets": 2, "reqlevel": 85, "sellprice": 122341, "slotbak": 5, "socket1": 2, "socket2": 3, "socketbonus": 4137, "sta": 454}, "56537": {"agi": 233, "appearances": {"0": [98750, ""]}, "armor": 939, "displayid": 98750, "dura": 55, "hitrtng": 174, "mastrtng": 134, "nsockets": 1, "reqlevel": 85, "sellprice": 44615, "slotbak": 6, "socket1": 2, "socketbonus": 2782, "sta": 380}, "58132": {"agi": 262, "appearances": {"0": [76597, ""]}, "armor": 1374, "displayid": 76597, "dura": 100, "exprtng": 162, "mastrtng": 202, "nsockets": 2, "reqlevel": 85, "slotbak": 7, "socket1": 2, "socket2": 4, "socketbonus": 4133, "sta": 454}, "56395": {"agi": 205, "appearances": {"0": [76440, ""]}, "armor": 1080, "displayid": 76440, "dura": 65, "hastertng": 130, "mastrtng": 150, "nsockets": 1, "reqlevel": 85, "sellprice": 91326, "slotbak": 8, "socket1": 4, "socketbonus": 4123, "sta": 337}, "65050": {"agi": 215, "appearances": {"0": [76665, ""]}, "armor": 775, "critstrkrtng": 143, "displayid": 76665, "dura": 55, "mastrtng": 143, "reqlevel": 85, "sellprice": 89846, "slotbak": 9, "sta": 322}, "62433": {"agi": 233, "appearances": {"0": [82020, ""]}, "armor": 1043, "buyprice": 425850, "critstrkrtng": 149, "displayid": 82020, "dura": 55, "hastertng": 169, "nsockets": 1, "reqfaction": 1174, "reqlevel": 85, "reqrep": 7, "sellprice": 85170, "slotbak": 10, "socket1": 3, "socketbonus": 4146, "sta": 380}, "62348": {"agi": 168, "buyprice": 213737, "hitrtng": 112, "mastrtng": 112, "reqfaction": 1171, "reqlevel": 85, "reqrep": 6, "sellprice": 53434, "slotbak": 11, "sta": 252}, "62361": {"agi": 168, "appearances": {"0": [83349, ""]}, "armor": 580, "buyprice": 371087, "displayid": 83349, "hastertng": 112, "hitrtng": 112, "reqfaction": 1135, "reqlevel": 85, "reqrep": 6, "sellprice": 74217, "slotbak": 16, "sta": 252}, "65081": {"agi": 165, "appearances": {"0": [71105, ""]}, "displayid": 71105, "dmgmax1": 1127, "dmgmin1": 751, "dmgrange": 0.4, "dmgtype1": 0, "dps": 521.67, "dura": 75, "exprtng": 110, "mastrtng": 110, "mledmgmax": 1127, "mledmgmin": 751, "mledps": 521.67, "mlespeed": 1.8, "reqlevel": 85, "sellprice": 347548, "sheathtype": 3, "slotbak": 13, "speed": 1.8, "sta": 248}, "56329": {"agi": 129, "appearances": {"0": [76996, ""]}, "critstrkrtng": 86, "displayid": 76996, "dmgmax1": 1384, "dmgmin1": 745, "dmgrange": 0.6, "dmgtype1": 0, "dps": 409.42, "dura": 65, "hastertng": 86, "mledmgmax": 1384, "mledmgmin": 745, "mledps": 409.42, "mlespeed": 2.6, "reqlevel": 85, "sellprice": 256438, "sheathtype": 7, "slotbak": 21, "speed": 2.6, "sta": 194}, "57927": {"agi": 129, "appearances": {"0": [83348, ""]}, "critstrkrtng": 86, "displayid": 83348, "dmgmax1": 745, "dmgmin1": 401, "dmgrange": 0.6, "dmgtype1": 0, "dps": 409.29, "dura": 65, "hitrtng": 86, "mledmgmax": 745, "mledmgmin": 401, "mledps": 409.29, "mlespeed": 1.4, "reqlevel": 85, "sheathtype": 3, "slotbak": 22, "speed": 1.4, "sta": 194}, "56420": {"agi": 95, "appearances": {"0": [76987, ""]}, "critstrkrtng": 63, "displayid": 76987, "dmgmax1": 1325, "dmgmin1": 883, "dmgrange": 0.4, "dmgtype1": 0, "dps": 552.0, "hitrtng": 63, "reqlevel": 85, "sellprice": 43988, "slotbak": 25, "speed": 2.0, "sta": 143}, "56336": {"appearances": {"0": [87531, ""]}, "armor": 2061, "critstrkrtng": 131, "displayid": 87531, "dura": 45, "hastertng": 141, "nsockets": 1, "reqlevel": 85, "sellprice": 86075, "slotbak": 10, "socket1": 2, "socketbonus": 4146, "sta": 337, "str": 205}, "56384": {"appearances": {"0": [77042, ""]}, "displayid": 77042, "dmgmax1": 1384, "dmgmin1": 745, "dmgrange": 0.6, "dmgtype1": 0, "dps": 409.42, "dura": 90, "hastertng": 86, "hitrtng": 86, "mledmgmax": 1384, "mledmgmin": 745, "mledps": 409.42, "mlespeed": 2.6, "reqlevel": 85, "sellprice": 258377, "sheathtype": 3, "slotbak": 13, "speed": 2.6, "sta": 194, "str": 129}, "57929": {"appearances": {"0": [83345, ""]}, "critstrkrtng": 86, "displayid": 83345, "dmgmax1": 1384, "dmgmin1": 745, "dmgrange": 0.6, "dmgtype1": 0, "dps": 409.42, "dura": 90, "exprtng": 86, "mledmgmax": 1384, "mledmgmin": 745, "mledps": 409.42, "mlespeed": 2.6, "reqlevel": 85, "sheathtype": 3, "slotbak": 22, "speed": 2.6, "sta": 194, "str": 129}, "63480": {"hastertng": 63, "mastrtng": 63, "nsockets": 1, "reqlevel": 85, "sellprice": 71204, "slotbak": 28, "socket1": 7, "sta": 143, "str": 95}, "58155": {"appearances": {"0": [95876, ""]}, "armor": 942, "critstrkrtng": 182, "displayid": 95876, "dura": 80, "hitrtng": 162, "int": 242, "nsockets": 2, "reqlevel": 85, "slotbak": 1, "socket1": 1, "socket2": 4, "socketbonus": 4150, "sta": 454}, "52291": {"avgbuyout": 6009997, "mlecritstrkrtng": 54, "rgdcritstrkrtng": 54, "sellprice": 37500, "splcritstrkrtng": 54, "meta": {"0": 3}}, "58157": {"appearances": {"0": [71213, ""]}, "armor": 870, "critstrkrtng": 130, "displayid": 71213, "dmgrange": 0.2, "dura": 80, "int": 205, "mastrtng": 150, "nsockets": 1, "reqlevel": 85, "slotbak": 3, "socket1": 3, "socketbonus": 4143, "sta": 337}, "62441": {"appearances": {"0": [76562, ""]}, "armor": 1160, "buyprice": 507707, "critstrkrtng": 172, "displayid": 76562, "dura": 135, "hitrtng": 192, "int": 262, "nsockets": 2, "reqfaction": 1173, "reqlevel": 85, "reqrep": 6, "sellprice": 101541, "slotbak": 20, "socket1": 3, "socket2": 4, "socketbonus": 4144, "sta": 454}, "65044": {"appearances": {"0": [82061, ""]}, "armor": 1177, "critstrkrtng": 217, "displayid": 82061, "dmgrange": 0.2, "dura": 120, "hitrtng": 257, "int": 345, "nsockets": 2, "reqlevel": 85, "sellprice": 136857, "slotbak": 7, "socket1": 3, "socket2": 4, "socketbonus": 4144, "sta": 578}, "62427": {"buyprice": 213737, "hitrtng": 112, "int": 168, "mastrtng": 112, "reqfaction": 1174, "reqlevel": 85, "reqrep": 6, "sellprice": 53434, "slotbak": 11, "sta": 252}, "56271": {"appearances": {"0": [76997, ""]}, "displayid": 76997, "dmgmax1": 1392, "dmgmin1": 927, "dmgrange": 0.4, "dmgtype1": 0, "dps": 552.14, "dura": 100, "hastertng": 202, "hitrtng": 202, "int": 302, "mledmgmax": 1392, "mledmgmin": 927, "mledps": 552.14, "mlespeed": 2.1, "reqlevel": 85, "sellprice": 322972, "sheathtype": 2, "slotbak": 17, "speed": 2.1, "spldmg": 1732, "splheal": 1732, "sta": 454}, "56338": {"agi": 168, "critstrkrtng": 112, "mastrtng": 112, "reqlevel": 85, "sellprice": 53434, "slotbak": 2, "sta": 252}, "63449": {"agi": 205, "appearances": {"0": [76446, ""]}, "armor": 1178, "critstrkrtng": 130, "displayid": 76446, "dura": 80, "hastertng": 150, "nsockets": 1, "reqlevel": 85, "sellprice": 92109, "slotbak": 3, "socket1": 3, "socketbonus": 4140, "sta": 337}, "57918": {"agi": 205, "appearances": {"0": [76592, ""]}, "armor": 884, "displayid": 76592, "dura": 45, "exprtng": 130, "mastrtng": 150, "nsockets": 1, "reqlevel": 85, "slotbak": 6, "socket1": 2, "socketbonus": 4123, "sta": 337}, "65178": {"agi": 205, "appearances": {"0": [76440, ""]}, "armor": 1080, "displayid": 76440, "dmgrange": 0.2, "dura": 65, "hastertng": 150, "mastrtng": 130, "nsockets": 1, "reqlevel": 85, "sellprice": 92501, "slotbak": 8, "socket1": 3, "socketbonus": 2782, "sta": 337}, "63454": {"agi": 168, "appearances": {"0": [76447, ""]}, "armor": 687, "critstrkrtng": 112, "displayid": 76447, "dura": 45, "mastrtng": 112, "reqlevel": 85, "sellprice": 62550, "slotbak": 9, "sta": 252}, "56412": {"agi": 168, "hastertng": 112, "mastrtng": 112, "reqlevel": 85, "sellprice": 53434, "slotbak": 11, "sta": 252}, "63473": {"agi": 168, "appearances": {"0": [83976, ""]}, "armor": 580, "critstrkrtng": 112, "displayid": 83976, "mastrtng": 112, "reqlevel": 85, "sellprice": 76752, "slotbak": 16, "sta": 252}, "56302": {"agi": 129, "appearances": {"0": [76986, ""]}, "displayid": 76986, "dmgmax1": 885, "dmgmin1": 589, "dmgrange": 0.4, "dmgtype1": 0, "dps": 409.44, "dura": 65, "hitrtng": 93, "mastrtng": 76, "mledmgmax": 885, "mledmgmin": 589, "mledps": 409.44, "mlespeed": 1.8, "reqlevel": 85, "sellprice": 243488, "sheathtype": 3, "slotbak": 13, "speed": 1.8, "sta": 194}, "66972": {"agi": 115, "appearances": {"0": [83354, ""]}, "avgbuyout": 5199999, "critstrkrtng": 76, "displayid": 83354, "dmgmax1": 1226, "dmgmin1": 660, "dmgrange": 0.6, "dmgtype1": 0, "dps": 362.69, "dura": 65, "hastertng": 76, "mledmgmax": 1226, "mledmgmin": 660, "mledps": 362.69, "mlespeed": 2.6, "reqlevel": 85, "sellprice": 243019, "sheathtype": 7, "slotbak": 21, "speed": 2.6, "sta": 172}, "56335": {"agi": 129, "appearances": {"0": [76984, ""]}, "displayid": 76984, "dmgmax1": 688, "dmgmin1": 458, "dmgrange": 0.4, "dmgtype1": 0, "dps": 409.29, "dura": 65, "hastertng": 86, "mastrtng": 86, "mledmgmax": 688, "mledmgmin": 458, "mledps": 409.29, "mlespeed": 1.4, "reqlevel": 85, "sellprice": 243638, "sheathtype": 3, "slotbak": 13, "speed": 1.4, "sta": 194}, "59598": {"agi": 84, "appearances": {"0": [69859, ""]}, "avgbuyout": 249889, "critstrkrtng": 49, "displayid": 69859, "dmgmax1": 1844, "dmgmin1": 993, "dmgrange": 0.6, "dmgtype1": 0, "dps": 489.14, "dura": 75, "hastertng": 60, "reqlevel": 83, "rgddmgmax": 1844, "rgddmgmin": 993, "rgddps": 489.14, "rgdspeed": 2.9, "sellprice": 184815, "slotbak": 26, "speed": 2.9, "sta": 126}, "63463": {"appearances": {"0": [76481, ""]}, "armor": 870, "displayid": 76481, "dmgrange": 0.2, "dura": 80, "hitrtng": 130, "int": 205, "mastrtng": 150, "nsockets": 1, "reqlevel": 85, "sellprice": 72040, "slotbak": 3, "socket1": 3, "socketbonus": 4143, "sta": 337}, "65034": {"appearances": {"0": [82055, ""]}, "armor": 757, "critstrkrtng": 171, "displayid": 82055, "dura": 55, "hastertng": 191, "int": 266, "nsockets": 1, "reqlevel": 85, "sellprice": 72929, "slotbak": 6, "socket1": 3, "socketbonus": 4211, "sta": 429}, "65069": {"appearances": {"0": [81954, ""]}, "armor": 925, "displayid": 81954, "dura": 75, "hastertng": 191, "int": 266, "mastrtng": 171, "nsockets": 1, "reqlevel": 85, "sellprice": 107410, "slotbak": 8, "socket1": 2, "socketbonus": 4146, "sta": 429}, "56357": {"appearances": {"0": [83509, ""]}, "critstrkrtng": 98, "displayid": 83509, "dmgmax1": 958, "dmgmin1": 516, "dmgrange": 0.6, "dmgtype1": 0, "dps": 409.44, "dura": 65, "hastertng": 66, "int": 130, "mledmgmax": 958, "mledmgmin": 516, "mledps": 409.44, "mlespeed": 1.8, "reqlevel": 85, "sellprice": 245427, "sheathtype": 3, "slotbak": 21, "speed": 1.8, "spldmg": 1729, "splheal": 1729, "sta": 194}, "65133": {"appearances": {"0": [82626, ""]}, "displayid": 82626, "hastertng": 143, "hitrtng": 143, "int": 215, "reqlevel": 85, "sellprice": 53434, "slotbak": 23, "sta": 322}, "57923": {"appearances": {"0": [82728, ""]}, "displayid": 82728, "hastertng": 112, "hitrtng": 112, "int": 168, "reqlevel": 85, "slotbak": 23, "sta": 252}, "56359": {"appearances": {"0": [76414, ""]}, "armor": 1741, "critstrkrtng": 114, "displayid": 76414, "dura": 80, "hastertng": 151, "int": 205, "nsockets": 1, "reqlevel": 85, "sellprice": 111753, "slotbak": 3, "socket1": 4, "socketbonus": 4143, "sta": 337}, "60201": {"appearances": {"0": [82051, ""]}, "armor": 2129, "displayid": 82051, "dura": 120, "hastertng": 228, "int": 301, "nsockets": 2, "reqlevel": 85, "sellprice": 210446, "slotbak": 7, "socket1": 2, "socket2": 4, "socketbonus": 4144, "spi": 188, "sta": 512}, "65068": {"appearances": {"0": [81289, ""]}, "armor": 1115, "displayid": 81289, "dura": 55, "int": 215, "mastrtng": 143, "reqlevel": 85, "sellprice": 107016, "slotbak": 9, "spi": 143, "sta": 322}, "60314": {"appearances": {"0": [82050, ""]}, "armor": 1521, "classes": 64, "critstrkrtng": 169, "displayid": 82050, "dmgrange": 0.2, "dura": 55, "hastertng": 149, "int": 233, "itemset": 940, "nsockets": 1, "reqlevel": 85, "slotbak": 10, "socket1": 4, "socketbonus": 4143, "sta": 380}, "56371": {"appearances": {"0": [83955, ""]}, "armor": 580, "critstrkrtng": 128, "displayid": 83955, "hitrtng": 85, "int": 168, "reqlevel": 85, "sellprice": 71972, "slotbak": 16, "sta": 252}, "64673": {"critstrkrtng": 72, "int": 107, "nsockets": 1, "reqlevel": 85, "slotbak": 28, "socket1": 7, "spi": 72, "sta": 161}, "52205": {"avgbuyout": 1990000, "int": 20, "mastrtng": 20, "sellprice": 37500, "color": 5}, "60251": {"appearances": {"0": [94248, ""]}, "armor": 1251, "classes": 256, "critstrkrtng": 218, "displayid": 94248, "dura": 165, "hastertng": 198, "int": 301, "itemset": 941, "nsockets": 2, "reqlevel": 85, "slotbak": 20, "socket1": 2, "socket2": 4, "socketbonus": 4144, "sta": 512}, "54506": {"appearances": {"0": [77132, ""]}, "armor": 1094, "critstrkrtng": 185, "displayid": 77132, "dmgrange": 0.2, "dura": 120, "int": 321, "mastrtng": 241, "nsockets": 1, "reqlevel": 85, "sellprice": 65264, "slotbak": 7, "socket1": 3, "socketbonus": 4123, "sta": 512}, "67131": {"appearances": {"0": [79321, ""]}, "armor": 625, "displayid": 79321, "hastertng": 107, "int": 170, "mastrtng": 127, "nsockets": 1, "reqlevel": 85, "sellprice": 99205, "slotbak": 16, "socket1": 3, "socketbonus": 4143, "sta": 286}, "59460": {"appearances": {"0": [82618, ""]}, "displayid": 82618, "dmgrange": 0.6, "dps": 880.56, "dura": 75, "hitrtng": 72, "int": 107, "mastrtng": 72, "reqlevel": 85, "sellprice": 253500, "slotbak": 26, "speed": 1.8, "sta": 161}, "60253": {"appearances": {"0": [91254, ""]}, "armor": 938, "classes": 16, "displayid": 91254, "dmgrange": 0.2, "dura": 100, "hastertng": 169, "int": 233, "itemset": 936, "nsockets": 1, "reqlevel": 85, "slotbak": 3, "socket1": 2, "socketbonus": 4146, "spi": 149, "sta": 380}, "56324": {"appearances": {"0": [76506, ""]}, "armor": 870, "displayid": 76506, "dmgrange": 0.2, "dura": 80, "hastertng": 111, "int": 205, "nsockets": 1, "reqlevel": 85, "sellprice": 75567, "slotbak": 3, "socket1": 3, "socketbonus": 4146, "spi": 161, "sta": 337}, "60254": {"appearances": {"0": [92243, ""]}, "armor": 1251, "classes": 16, "critstrkrtng": 218, "displayid": 92243, "dura": 165, "hastertng": 198, "int": 301, "itemset": 936, "nsockets": 2, "reqlevel": 85, "slotbak": 20, "socket1": 2, "socket2": 4, "socketbonus": 4144, "sta": 512}, "56318": {"appearances": {"0": [76746, ""]}, "armor": 2474, "displayid": 76746, "dura": 80, "hitrtng": 111, "mastrtng": 161, "nsockets": 1, "reqlevel": 85, "sellprice": 125660, "slotbak": 3, "socket1": 2, "socketbonus": 4141, "sta": 337, "str": 205}, "56447": {"appearances": {"0": [76381, ""]}, "armor": 1855, "critstrkrtng": 130, "displayid": 76381, "dura": 45, "hastertng": 150, "nsockets": 1, "reqlevel": 85, "sellprice": 83118, "slotbak": 6, "socket1": 3, "socketbonus": 4146, "sta": 337, "str": 205}, "60340": {"appearances": {"0": [81304, ""]}, "armor": 2141, "classes": 32, "displayid": 81304, "dura": 55, "hastertng": 169, "itemset": 925, "mastrtng": 149, "nsockets": 1, "reqlevel": 85, "slotbak": 10, "socket1": 4, "socketbonus": 4135, "sta": 380, "str": 233}, "67139": {"hastertng": 127, "mastrtng": 127, "reqlevel": 85, "sellprice": 53434, "slotbak": 11, "sta": 286, "str": 190}, "60344": {"appearances": {"0": [79839, ""]}, "armor": 3426, "classes": 2, "critstrkrtng": 228, "displayid": 79839, "dura": 165, "hastertng": 188, "itemset": 932, "nsockets": 2, "reqlevel": 85, "slotbak": 5, "socket1": 2, "socket2": 4, "socketbonus": 4136, "sta": 512, "str": 301}, "62432": {"appearances": {"0": [76720, ""]}, "armor": 2355, "buyprice": 889252, "displayid": 76720, "dura": 75, "mastrtng": 159, "nsockets": 1, "parryrtng": 139, "reqfaction": 1174, "reqlevel": 85, "reqrep": 7, "sellprice": 177850, "slotbak": 8, "socket1": 3, "socketbonus": 4147, "sta": 380, "str": 253}, "56388": {"critstrkrtng": 98, "mastrtng": 120, "reqlevel": 85, "sellprice": 53434, "slotbak": 11, "sta": 252, "str": 168}, "56397": {"appearances": {"0": [83349, ""]}, "armor": 580, "critstrkrtng": 120, "displayid": 83349, "hitrtng": 98, "reqlevel": 85, "sellprice": 73605, "slotbak": 16, "sta": 252, "str": 168}, "56279": {"critstrkrtng": 60, "hitrtng": 65, "nsockets": 1, "reqlevel": 85, "sellprice": 72241, "slotbak": 28, "socket1": 7, "sta": 143, "str": 95}, "59453": {"appearances": {"0": [65425, ""]}, "armor": 1356, "displayid": 65425, "dura": 100, "int": 301, "nsockets": 3, "reqlevel": 85, "reqskill": 202, "reqskillrank": 525, "sellprice": 123440, "slotbak": 1, "socket1": 1, "socket2": 6, "socket3": 6, "socketbonus": 4144, "sta": 512}, "65078": {"appearances": {"0": [81711, ""]}, "armor": 1328, "displayid": 81711, "dura": 100, "hastertng": 191, "int": 266, "nsockets": 1, "reqlevel": 85, "sellprice": 138676, "slotbak": 3, "socket1": 2, "socketbonus": 4142, "spi": 171, "sta": 429}, "56561": {"appearances": {"0": [81706, ""]}, "armor": 1669, "critstrkrtng": 205, "displayid": 81706, "dura": 165, "int": 321, "mastrtng": 221, "nsockets": 1, "reqlevel": 85, "sellprice": 84165, "slotbak": 5, "socket1": 2, "socketbonus": 4211, "sta": 512}, "62431": {"appearances": {"0": [98751, ""]}, "armor": 939, "buyprice": 422716, "displayid": 98751, "dura": 55, "hastertng": 149, "int": 233, "nsockets": 1, "reqfaction": 1174, "reqlevel": 85, "reqrep": 7, "sellprice": 84543, "slotbak": 6, "socket1": 3, "socketbonus": 4142, "spi": 169, "sta": 380}, "60283": {"appearances": {"0": [76689, ""]}, "armor": 1460, "classes": 1024, "displayid": 76689, "dura": 120, "hastertng": 228, "int": 301, "itemset": 929, "nsockets": 2, "reqlevel": 85, "slotbak": 7, "socket1": 2, "socket2": 4, "socketbonus": 4144, "spi": 188, "sta": 512}, "56277": {"appearances": {"0": [85937, ""]}, "armor": 1080, "critstrkrtng": 151, "displayid": 85937, "dura": 65, "int": 205, "nsockets": 1, "reqlevel": 85, "sellprice": 89611, "slotbak": 8, "socket1": 2, "socketbonus": 4131, "spi": 114, "sta": 337}, "56297": {"appearances": {"0": [85944, ""]}, "armor": 687, "critstrkrtng": 98, "displayid": 85944, "dura": 45, "hastertng": 120, "int": 168, "reqlevel": 85, "sellprice": 59735, "slotbak": 9, "sta": 252}, "56334": {"appearances": {"0": [85965, ""]}, "armor": 982, "displayid": 85965, "dura": 45, "hastertng": 130, "int": 205, "nsockets": 1, "reqlevel": 85, "sellprice": 59032, "slotbak": 10, "socket1": 4, "socketbonus": 4143, "spi": 150, "sta": 337}, "65186": {"appearances": {"0": [90586, ""]}, "armor": 2891, "classes": 32, "displayid": 90586, "dodgertng": 325, "dura": 100, "hitrtng": 135, "itemset": -283, "nsockets": 2, "reqlevel": 85, "slotbak": 1, "socket1": 1, "socket2": 3, "socketbonus": 4159, "sta": 578, "str": 293}, "65059": {"dodgertng": 215, "hitrtng": 109, "reqlevel": 85, "sellprice": 53434, "slotbak": 2, "sta": 322, "str": 163}, "65188": {"appearances": {"0": [90587, ""]}, "armor": 2669, "classes": 32, "displayid": 90587, "dodgertng": 246, "dura": 100, "hitrtng": 145, "itemset": -283, "nsockets": 1, "reqlevel": 85, "slotbak": 3, "socket1": 2, "socketbonus": 4154, "sta": 429, "str": 217}, "52215": {"avgbuyout": 1990096, "mastrtng": 20, "parryrtng": 20, "sellprice": 37500, "color": 5}, "65184": {"appearances": {"0": [78792, ""]}, "armor": 3559, "classes": 32, "displayid": 78792, "dura": 165, "itemset": -283, "mastrtng": 237, "nsockets": 2, "parryrtng": 197, "reqlevel": 85, "slotbak": 5, "socket1": 2, "socket2": 4, "socketbonus": 4134, "sta": 578, "str": 385}, "65370": {"appearances": {"0": [82121, ""]}, "armor": 2002, "displayid": 82121, "dura": 55, "nsockets": 1, "reqlevel": 85, "sellprice": 126979, "slotbak": 6, "socket1": 2, "socketbonus": 4154}, "67141": {"appearances": {"0": [76715, ""]}, "armor": 2998, "displayid": 76715, "dura": 120, "hastertng": 241, "hitrtng": 165, "nsockets": 2, "reqlevel": 85, "sellprice": 246674, "slotbak": 7, "socket1": 3, "socket2": 3, "socketbonus": 4140, "sta": 512, "str": 301}, "60229": {"appearances": {"0": [82098, ""]}, "armor": 2497, "displayid": 82098, "dodgertng": 184, "dura": 75, "nsockets": 2, "parryrtng": 144, "reqlevel": 85, "sellprice": 185306, "slotbak": 8, "socket1": 2, "socket2": 4, "socketbonus": 4134, "sta": 458, "str": 306}, "52243": {"avgbuyout": 1999998, "sellprice": 37500, "sta": 30, "str": 20, "color": 3}, "65185": {"appearances": {"0": [78787, ""]}, "armor": 2224, "classes": 32, "displayid": 78787, "dura": 55, "itemset": -283, "mastrtng": 171, "nsockets": 1, "parryrtng": 171, "reqlevel": 85, "slotbak": 10, "socket1": 4, "socketbonus": 4123, "sta": 429, "str": 286}, "65372": {"reqlevel": 85, "sellprice": 53434, "slotbak": 11}, "69878": {"appearances": {"0": [61031, "inv_misc_cape_16"]}, "armor": 673, "displayid": 61031, "reqlevel": 85, "sellprice": 103517, "slotbak": 16}, "65007": {"appearances": {"0": [71121, ""]}, "displayid": 71121, "dmgmax1": 3040, "dmgmin1": 2026, "dmgrange": 0.4, "dmgtype1": 0, "dps": 703.61, "dura": 120, "exprtng": 257, "mastrtng": 257, "mledmgmax": 3040, "mledmgmin": 2026, "mledps": 703.61, "mlespeed": 3.6, "reqlevel": 85, "sellprice": 432702, "sheathtype": 1, "slotbak": 17, "speed": 3.6, "sta": 578, "str": 385}, "65107": {"agi": 215, "hastertng": 143, "mastrtng": 143, "reqlevel": 85, "sellprice": 53434, "slotbak": 2, "sta": 322}, "67137": {"agi": 190, "hastertng": 96, "mastrtng": 145, "reqlevel": 85, "sellprice": 53434, "slotbak": 2, "sta": 286}, "58134": {"agi": 205, "appearances": {"0": [81374, ""]}, "armor": 1178, "critstrkrtng": 150, "displayid": 81374, "dura": 80, "hitrtng": 130, "nsockets": 1, "reqlevel": 85, "slotbak": 3, "socket1": 4, "socketbonus": 2782, "sta": 337}, "60287": {"agi": 301, "appearances": {"0": [76698, ""]}, "armor": 1669, "classes": 1024, "displayid": 76698, "dura": 165, "exprtng": 188, "hastertng": 228, "itemset": 927, "nsockets": 2, "reqlevel": 85, "slotbak": 20, "socket1": 2, "socket2": 4, "socketbonus": 4133, "sta": 512}, "63435": {"agi": 205, "appearances": {"0": [76440, ""]}, "armor": 1080, "critstrkrtng": 150, "displayid": 76440, "dura": 65, "hitrtng": 130, "nsockets": 1, "reqlevel": 85, "sellprice": 94179, "slotbak": 8, "socket1": 3, "socketbonus": 4151, "sta": 337}, "65073": {"agi": 266, "appearances": {"0": [76662, ""]}, "armor": 1107, "displayid": 76662, "dura": 55, "exprtng": 171, "mastrtng": 191, "nsockets": 1, "reqlevel": 85, "sellprice": 90815, "slotbak": 10, "socket1": 2, "socketbonus": 4123, "sta": 429}, "65082": {"agi": 215, "critstrkrtng": 143, "hitrtng": 143, "reqlevel": 85, "sellprice": 53434, "slotbak": 11, "sta": 322}, "67136": {"agi": 190, "hastertng": 138, "hitrtng": 108, "reqlevel": 85, "sellprice": 53434, "slotbak": 11, "sta": 286}, "65035": {"agi": 215, "appearances": {"0": [84194, ""]}, "armor": 673, "critstrkrtng": 143, "displayid": 84194, "mastrtng": 143, "reqlevel": 85, "sellprice": 109789, "slotbak": 16, "sta": 322}, "56343": {"agi": 302, "appearances": {"0": [73032, ""]}, "displayid": 73032, "dmgmax1": 1590, "dmgmin1": 1060, "dmgrange": 0.4, "dmgtype1": 0, "dps": 552.08, "dura": 100, "hitrtng": 202, "mastrtng": 202, "mledmgmax": 1590, "mledmgmin": 1060, "mledps": 552.08, "mlespeed": 2.4, "reqlevel": 85, "sellprice": 313682, "sheathtype": 2, "slotbak": 17, "speed": 2.4, "sta": 454}, "63460": {"agi": 95, "critstrkrtng": 63, "hastertng": 63, "nsockets": 1, "reqlevel": 85, "sellprice": 71212, "slotbak": 28, "socket1": 7, "sta": 143}, "60352": {"appearances": {"0": [81305, ""]}, "armor": 2998, "classes": 32, "displayid": 81305, "dmgrange": 0.2, "dodgertng": 188, "dura": 120, "itemset": 926, "nsockets": 2, "parryrtng": 228, "reqlevel": 85, "slotbak": 7, "socket1": 2, "socket2": 4, "socketbonus": 4134, "sta": 512, "str": 301}, "63444": {"appearances": {"0": [76390, ""]}, "armor": 2268, "displayid": 76390, "dodgertng": 130, "dura": 65, "nsockets": 1, "parryrtng": 130, "reqlevel": 85, "sellprice": 126324, "slotbak": 8, "socket1": 3, "socketbonus": 4154, "sta": 337, "str": 225}, "58105": {"appearances": {"0": [82126, ""]}, "armor": 2061, "displayid": 82126, "dodgertng": 130, "dura": 45, "mastrtng": 140, "nsockets": 1, "reqlevel": 85, "slotbak": 10, "socket1": 4, "socketbonus": 4155, "sta": 337, "str": 215}, "62351": {"buyprice": 213737, "dodgertng": 112, "mastrtng": 112, "reqfaction": 1171, "reqlevel": 85, "reqrep": 6, "sellprice": 53434, "slotbak": 11, "sta": 252, "str": 168}, "65096": {"appearances": {"0": [90586, ""]}, "armor": 2891, "displayid": 90586, "dura": 100, "mastrtng": 197, "nsockets": 2, "parryrtng": 257, "reqlevel": 85, "sellprice": 178669, "slotbak": 1, "socket1": 1, "socket2": 3, "socketbonus": 4138, "sta": 578, "str": 325}, "60422": {"appearances": {"0": [86609, ""]}, "armor": 2615, "classes": 1, "displayid": 86609, "dura": 100, "exprtng": 159, "itemset": -317, "nsockets": 1, "reqlevel": 85, "resirtng": 179, "sellprice": 183400, "slotbak": 3, "socket1": 3, "socketbonus": 4135, "sta": 402, "str": 248}, "60419": {"appearances": {"0": [63359, ""]}, "armor": 2179, "classes": 1, "displayid": 63359, "dura": 55, "hitrtng": 159, "itemset": -317, "nsockets": 1, "reqlevel": 85, "resirtng": 179, "sellprice": 121848, "slotbak": 10, "socket1": 4, "socketbonus": 4135, "sta": 402, "str": 248}, "56364": {"appearances": {"0": [77007, ""]}, "displayid": 77007, "dmgmax1": 1384, "dmgmin1": 745, "dmgrange": 0.6, "dmgtype1": 0, "dps": 409.42, "dura": 90, "hitrtng": 66, "mastrtng": 98, "mledmgmax": 1384, "mledmgmin": 745, "mledps": 409.42, "mlespeed": 2.6, "reqlevel": 85, "sellprice": 251815, "sheathtype": 3, "slotbak": 13, "speed": 2.6, "sta": 194, "str": 129}, "65023": {"appearances": {"0": [71431, ""]}, "armor": 12103, "displayid": 71431, "dura": 120, "mastrtng": 143, "parryrtng": 143, "reqlevel": 85, "sellprice": 218153, "sheathtype": 4, "slotbak": 14, "sta": 322, "str": 215}, "56317": {"agi": 95, "appearances": {"0": [76999, ""]}, "critstrkrtng": 68, "displayid": 76999, "dmgmax1": 2082, "dmgmin1": 1121, "dmgrange": 0.6, "dmgtype1": 2, "dps": 552.24, "dura": 75, "hitrtng": 56, "reqlevel": 85, "rgddmgmax": 2082, "rgddmgmin": 1121, "rgddps": 552.24, "rgdspeed": 2.9, "sellprice": 179167, "slotbak": 15, "speed": 2.9, "sta": 143}, "65043": {"appearances": {"0": [91290, ""]}, "armor": 1009, "critstrkrtng": 176, "displayid": 91290, "dmgrange": 0.2, "dura": 100, "int": 266, "nsockets": 1, "reqlevel": 85, "sellprice": 102248, "slotbak": 3, "socket1": 3, "socketbonus": 4142, "spi": 186, "sta": 429}, "65032": {"appearances": {"0": [82006, ""]}, "armor": 1177, "critstrkrtng": 247, "displayid": 82006, "dmgrange": 0.2, "dura": 120, "int": 345, "nsockets": 2, "reqlevel": 85, "sellprice": 144821, "slotbak": 7, "socket1": 2, "socket2": 3, "socketbonus": 4152, "spi": 227, "sta": 578}, "63437": {"appearances": {"0": [76500, ""]}, "armor": 507, "displayid": 76500, "dura": 45, "int": 168, "mastrtng": 112, "reqlevel": 85, "sellprice": 50596, "slotbak": 9, "spi": 112, "sta": 252}, "58188": {"critstrkrtng": 127, "hastertng": 127, "int": 190, "reqlevel": 85, "slotbak": 11, "sta": 286}, "65111": {"appearances": {"0": [82627, ""]}, "displayid": 82627, "int": 215, "mastrtng": 143, "reqlevel": 85, "sellprice": 53434, "slotbak": 23, "spi": 143, "sta": 322}, "65064": {"appearances": {"0": [77148, ""]}, "displayid": 77148, "dmgrange": 0.6, "dps": 994.17, "dura": 75, "int": 121, "mastrtng": 81, "reqlevel": 85, "sellprice": 263620, "slotbak": 26, "speed": 1.8, "spi": 81, "sta": 181}, "65136": {"appearances": {"0": [89762, ""]}, "armor": 2071, "displayid": 89762, "dura": 100, "hastertng": 165, "int": 325, "nsockets": 2, "reqlevel": 85, "sellprice": 153389, "slotbak": 1, "socket1": 1, "socket2": 4, "socketbonus": 4150, "spi": 276, "sta": 578}, "52257": {"int": 67, "reqskill": 755, "reqskillrank": 500, "sellprice": 11250, "color": 0}, "58127": {"appearances": {"0": [74915, ""]}, "armor": 2032, "displayid": 74915, "dura": 100, "hastertng": 192, "int": 262, "nsockets": 2, "reqlevel": 85, "slotbak": 7, "socket1": 2, "socket2": 3, "socketbonus": 4129, "spi": 172, "sta": 454}, "65033": {"appearances": {"0": [81283, ""]}, "armor": 1752, "displayid": 81283, "dura": 75, "int": 266, "mastrtng": 191, "nsockets": 1, "reqlevel": 85, "sellprice": 164242, "slotbak": 8, "socket1": 4, "socketbonus": 4123, "spi": 171, "sta": 429}, "56313": {"appearances": {"0": [76415, ""]}, "armor": 1016, "critstrkrtng": 112, "displayid": 76415, "dura": 45, "int": 168, "reqlevel": 85, "sellprice": 78042, "slotbak": 9, "spi": 112, "sta": 252}, "56402": {"appearances": {"0": [82869, ""]}, "armor": 11696, "displayid": 82869, "dura": 100, "hastertng": 120, "int": 168, "mastrtng": 98, "reqlevel": 85, "sellprice": 164168, "sheathtype": 4, "slotbak": 14, "sta": 252}, "67130": {"hastertng": 134, "int": 190, "mastrtng": 114, "reqlevel": 85, "sellprice": 53434, "slotbak": 2, "sta": 286}, "56361": {"appearances": {"0": [94259, ""]}, "armor": 1178, "displayid": 94259, "dura": 80, "hastertng": 150, "int": 205, "nsockets": 1, "reqlevel": 85, "sellprice": 93405, "slotbak": 3, "socket1": 2, "socketbonus": 4151, "spi": 130, "sta": 337}, "65374": {"appearances": {"0": [81712, ""]}, "armor": 996, "displayid": 81712, "dura": 55, "nsockets": 1, "reqlevel": 85, "sellprice": 91490, "slotbak": 6, "socket1": 3, "socketbonus": 4143}, "52232": {"avgbuyout": 1459966, "mlehastertng": 40, "rgdhastertng": 40, "sellprice": 37500, "splhastertng": 40, "color": 2}, "65384": {"appearances": {"0": [81708, ""]}, "armor": 1550, "displayid": 81708, "dura": 120, "nsockets": 2, "reqlevel": 85, "sellprice": 176422, "slotbak": 7, "socket1": 2, "socket2": 4, "socketbonus": 4149}, "58140": {"appearances": {"0": [76603, ""]}, "armor": 1374, "displayid": 76603, "dura": 100, "hastertng": 162, "int": 262, "mastrtng": 202, "nsockets": 2, "reqlevel": 85, "slotbak": 7, "socket1": 2, "socket2": 4, "socketbonus": 4152, "sta": 454}, "65128": {"appearances": {"0": [81705, ""]}, "armor": 1218, "critstrkrtng": 171, "displayid": 81705, "dura": 75, "int": 266, "nsockets": 1, "reqlevel": 85, "sellprice": 137249, "slotbak": 8, "socket1": 4, "socketbonus": 4143, "spi": 191, "sta": 429}, "60280": {"appearances": {"0": [76691, ""]}, "armor": 1043, "classes": 1024, "displayid": 76691, "dura": 55, "hastertng": 149, "int": 233, "itemset": 928, "nsockets": 1, "reqlevel": 85, "slotbak": 10, "socket1": 2, "socketbonus": 4142, "spi": 169, "sta": 380}, "65017": {"appearances": {"0": [71112, ""]}, "displayid": 71112, "dmgmax1": 1221, "dmgmin1": 657, "dmgrange": 0.6, "dmgtype1": 0, "dps": 521.67, "dura": 105, "int": 165, "mastrtng": 110, "mledmgmax": 1221, "mledmgmin": 657, "mledps": 521.67, "mlespeed": 1.8, "reqlevel": 85, "sellprice": 368630, "sheathtype": 3, "slotbak": 21, "speed": 1.8, "spi": 110, "spldmg": 2207, "splheal": 2207, "sta": 247}, "65137": {"appearances": {"0": [81972, ""]}, "armor": 3114, "displayid": 81972, "dura": 120, "hastertng": 217, "int": 345, "nsockets": 2, "reqlevel": 85, "sellprice": 239526, "slotbak": 7, "socket1": 2, "socket2": 4, "socketbonus": 4140, "spi": 257, "sta": 578}, "59516": {"appearances": {"0": [84201, ""]}, "armor": 625, "displayid": 84201, "hastertng": 127, "int": 190, "reqlevel": 85, "sellprice": 99844, "slotbak": 16, "spi": 127, "sta": 286}, "63680": {"appearances": {"0": [73030, ""]}, "critstrkrtng": 97, "displayid": 73030, "dmgmax1": 1022, "dmgmin1": 550, "dmgrange": 0.6, "dmgtype1": 0, "dps": 462.35, "dura": 105, "hastertng": 97, "int": 146, "mledmgmax": 1022, "mledmgmin": 550, "mledps": 462.35, "mlespeed": 1.7, "reqlevel": 85, "sellprice": 345729, "sheathtype": 3, "slotbak": 21, "speed": 1.7, "spldmg": 1954, "splheal": 1954, "sta": 219}, "65052": {"appearances": {"0": [75550, ""]}, "armor": 12103, "critstrkrtng": 143, "displayid": 75550, "dura": 120, "int": 215, "reqlevel": 85, "sellprice": 231691, "sheathtype": 4, "slotbak": 14, "spi": 143, "sta": 322}, "65046": {"appearances": {"0": [81282, ""]}, "armor": 1433, "critstrkrtng": 191, "displayid": 81282, "dura": 55, "int": 266, "nsockets": 1, "reqlevel": 85, "sellprice": 103421, "slotbak": 6, "socket1": 3, "socketbonus": 4151, "spi": 171, "sta": 429}, "65386": {"appearances": {"0": [89778, ""]}, "armor": 2230, "displayid": 89778, "dura": 120, "nsockets": 2, "reqlevel": 85, "sellprice": 213285, "slotbak": 7, "socket1": 2, "socket2": 4, "socketbonus": 4144}, "65221": {"appearances": {"0": [91388, ""]}, "armor": 2891, "classes": 2, "critstrkrtng": 197, "displayid": 91388, "dura": 100, "int": 325, "itemset": -290, "nsockets": 2, "reqlevel": 85, "slotbak": 1, "socket1": 1, "socket2": 4, "socketbonus": 4150, "spi": 257, "sta": 578}, "60360": {"appearances": {"0": [79839, ""]}, "armor": 3426, "classes": 2, "displayid": 79839, "dura": 165, "int": 301, "itemset": 933, "mastrtng": 188, "nsockets": 2, "reqlevel": 85, "slotbak": 5, "socket1": 3, "socket2": 4, "socketbonus": 4144, "spi": 228, "sta": 512}, "60234": {"appearances": {"0": [81971, ""]}, "armor": 1589, "displayid": 81971, "dura": 55, "hastertng": 133, "int": 209, "nsockets": 1, "reqlevel": 85, "sellprice": 126812, "slotbak": 9, "socket1": 3, "socketbonus": 4143, "spi": 153, "sta": 344}, "60323": {"appearances": {"0": [76718, ""]}, "armor": 3426, "classes": 1, "critstrkrtng": 228, "displayid": 76718, "dura": 165, "hastertng": 188, "itemset": 942, "nsockets": 2, "reqlevel": 85, "slotbak": 5, "socket1": 2, "socket2": 4, "socketbonus": 4136, "sta": 512, "str": 301}, "65369": {"appearances": {"0": [81290, ""]}, "armor": 2002, "displayid": 81290, "dura": 55, "nsockets": 1, "reqlevel": 85, "sellprice": 126516, "slotbak": 6, "socket1": 3, "socketbonus": 4135}, "60324": {"appearances": {"0": [76715, ""]}, "armor": 2998, "classes": 1, "displayid": 76715, "dura": 120, "hitrtng": 188, "itemset": 942, "mastrtng": 228, "nsockets": 2, "reqlevel": 85, "slotbak": 7, "socket1": 3, "socket2": 3, "socketbonus": 4140, "sta": 512, "str": 301}, "58195": {"appearances": {"0": [76720, ""]}, "armor": 2355, "critstrkrtng": 169, "displayid": 76720, "dura": 75, "hastertng": 149, "nsockets": 1, "reqlevel": 85, "slotbak": 8, "socket1": 3, "socketbonus": 4131, "sta": 380, "str": 233}, "69852": {"critstrkrtng": 109, "mastrtng": 94, "nsockets": 1, "reqlevel": 85, "sellprice": 55086, "slotbak": 11, "socket1": 2, "socketbonus": 4123, "sta": 252, "str": 148}, "60210": {"appearances": {"0": [71120, ""]}, "displayid": 71120, "dmgmax1": 2431, "dmgmin1": 1309, "dmgrange": 0.6, "dmgtype1": 3, "dps": 623.33, "dura": 95, "exprtng": 72, "mastrtng": 72, "reqlevel": 85, "rgddmgmax": 2431, "rgddmgmin": 1309, "rgddps": 623.33, "rgdspeed": 3.0, "sellprice": 252625, "slotbak": 26, "speed": 3.0, "sta": 161, "str": 107}, "65260": {"appearances": {"0": [91510, ""]}, "armor": 1093, "classes": 256, "displayid": 91510, "dura": 100, "hastertng": 217, "int": 325, "itemset": -298, "mastrtng": 237, "nsockets": 2, "reqlevel": 85, "slotbak": 1, "socket1": 1, "socket2": 4, "socketbonus": 4153, "sta": 578}, "57933": {"hitrtng": 112, "int": 168, "mastrtng": 112, "reqlevel": 85, "slotbak": 2, "sta": 252}, "65263": {"appearances": {"0": [91511, ""]}, "armor": 1009, "classes": 256, "displayid": 91511, "dmgrange": 0.2, "dura": 100, "hastertng": 191, "hitrtng": 171, "int": 266, "itemset": -298, "nsockets": 1, "reqlevel": 85, "slotbak": 3, "socket1": 2, "socketbonus": 4146, "sta": 429}, "56348": {"appearances": {"0": [76492, ""]}, "armor": 797, "displayid": 76492, "dura": 65, "hitrtng": 130, "int": 205, "mastrtng": 150, "nsockets": 1, "reqlevel": 85, "sellprice": 76648, "slotbak": 8, "socket1": 4, "socketbonus": 4143, "sta": 337}, "56106": {"critstrkrtng": 100, "hitrtng": 100, "int": 149, "reqlevel": 83, "sellprice": 53434, "slotbak": 11, "sta": 224}, "65041": {"appearances": {"0": [71109, ""]}, "displayid": 71109, "dmgmax1": 1221, "dmgmin1": 657, "dmgrange": 0.6, "dmgtype1": 0, "dps": 521.67, "dura": 75, "hastertng": 110, "int": 165, "mastrtng": 110, "mledmgmax": 1221, "mledmgmin": 657, "mledps": 521.67, "mlespeed": 1.8, "reqlevel": 85, "sellprice": 338234, "sheathtype": 3, "slotbak": 21, "speed": 1.8, "spldmg": 2207, "splheal": 2207, "sta": 248}, "65787": {"appearances": {"0": [77109, ""]}, "displayid": 77109, "dmgrange": 0.6, "dps": 568.42, "dura": 55, "hitrtng": 38, "int": 69, "mastrtng": 51, "sellprice": 145258, "slotbak": 26, "speed": 1.9, "sta": 104}, "65074": {"agi": 266, "appearances": {"0": [91207, ""]}, "armor": 1911, "critstrkrtng": 191, "displayid": 91207, "dmgrange": 0.2, "dura": 100, "mastrtng": 171, "nsockets": 1, "reqlevel": 85, "sellprice": 164788, "slotbak": 3, "socket1": 2, "socketbonus": 4123, "sta": 429}, "65204": {"agi": 345, "appearances": {"0": [81886, ""]}, "armor": 2548, "classes": 4, "displayid": 81886, "dura": 165, "hastertng": 217, "itemset": -287, "mastrtng": 257, "nsockets": 2, "reqlevel": 85, "slotbak": 5, "socket1": 2, "socket2": 4, "socketbonus": 4133, "sta": 578}, "60305": {"agi": 301, "appearances": {"0": [81817, ""]}, "armor": 2129, "classes": 4, "critstrkrtng": 228, "displayid": 81817, "dura": 120, "hastertng": 188, "itemset": 930, "nsockets": 2, "reqlevel": 85, "slotbak": 7, "socket1": 3, "socket2": 3, "socketbonus": 4133, "sta": 512}, "52209": {"agi": 20, "avgbuyout": 1499999, "mlecritstrkrtng": 20, "rgdcritstrkrtng": 20, "sellprice": 37500, "splcritstrkrtng": 20, "color": 5}, "65063": {"agi": 266, "appearances": {"0": [81884, ""]}, "armor": 1752, "displayid": 81884, "dura": 75, "hastertng": 191, "hitrtng": 171, "nsockets": 1, "reqlevel": 85, "sellprice": 158297, "slotbak": 8, "socket1": 4, "socketbonus": 2782, "sta": 429}, "65028": {"agi": 215, "appearances": {"0": [81881, ""]}, "armor": 1115, "critstrkrtng": 143, "displayid": 81881, "dura": 55, "hitrtng": 143, "reqlevel": 85, "sellprice": 104221, "slotbak": 9, "sta": 322}, "65367": {"reqlevel": 85, "sellprice": 53434, "slotbak": 11}, "69831": {"appearances": {"0": [84194, ""]}, "armor": 625, "displayid": 84194, "reqlevel": 85, "sellprice": 104965, "slotbak": 16}, "65139": {"agi": 385, "appearances": {"0": [69775, ""]}, "critstrkrtng": 257, "displayid": 69775, "dmgmax1": 2026, "dmgmin1": 1350, "dmgrange": 0.4, "dmgtype1": 0, "dps": 703.33, "dura": 120, "mastrtng": 257, "mledmgmax": 2026, "mledmgmin": 1350, "mledps": 703.33, "mlespeed": 2.4, "reqlevel": 85, "sellprice": 431013, "sheathtype": 2, "slotbak": 17, "speed": 2.4, "sta": 578}, "65058": {"agi": 121, "appearances": {"0": [71106, ""]}, "critstrkrtng": 81, "displayid": 71106, "dmgmax1": 2653, "dmgmin1": 1428, "dmgrange": 0.6, "dmgtype1": 2, "dps": 703.62, "dura": 90, "mastrtng": 81, "reqlevel": 85, "rgddmgmax": 2653, "rgddmgmin": 1428, "rgddps": 703.62, "rgdspeed": 2.9, "sellprice": 277379, "slotbak": 15, "speed": 2.9, "sta": 181}, "65243": {"agi": 266, "appearances": {"0": [76666, ""]}, "armor": 1328, "classes": 8, "critstrkrtng": 171, "displayid": 76666, "dura": 100, "hastertng": 191, "itemset": -294, "nsockets": 1, "reqlevel": 85, "slotbak": 3, "socket1": 4, "socketbonus": 2782, "sta": 429}, "65060": {"agi": 345, "appearances": {"0": [76669, ""]}, "armor": 1771, "critstrkrtng": 227, "displayid": 76669, "dura": 165, "mastrtng": 247, "nsockets": 2, "reqlevel": 85, "sellprice": 186234, "slotbak": 5, "socket1": 2, "socket2": 3, "socketbonus": 4137, "sta": 578}, "65381": {"appearances": {"0": [76667, ""]}, "armor": 1550, "displayid": 76667, "dura": 120, "nsockets": 2, "reqlevel": 85, "sellprice": 169756, "slotbak": 7, "socket1": 2, "socket2": 4, "socketbonus": 4133}, "58482": {"agi": 233, "appearances": {"0": [82018, ""]}, "armor": 1148, "critstrkrtng": 149, "displayid": 82018, "dura": 75, "hastertng": 169, "nsockets": 1, "reqlevel": 85, "slotbak": 8, "socket1": 4, "socketbonus": 2782, "sta": 380}, "56409": {"agi": 168, "appearances": {"0": [76447, ""]}, "armor": 687, "displayid": 76447, "dura": 45, "hastertng": 112, "hitrtng": 112, "reqlevel": 85, "sellprice": 59505, "slotbak": 9, "sta": 252}, "60298": {"agi": 233, "appearances": {"0": [82020, ""]}, "armor": 1043, "classes": 8, "displayid": 82020, "dura": 55, "hastertng": 169, "hitrtng": 149, "itemset": 937, "nsockets": 1, "reqlevel": 85, "slotbak": 10, "socket1": 2, "socketbonus": 4146, "sta": 380}, "67134": {"agi": 190, "appearances": {"0": [84194, ""]}, "armor": 625, "critstrkrtng": 127, "displayid": 84194, "hitrtng": 127, "reqlevel": 85, "sellprice": 100339, "slotbak": 16, "sta": 286}, "65024": {"agi": 165, "appearances": {"0": [71111, ""]}, "critstrkrtng": 110, "displayid": 71111, "dmgmax1": 1764, "dmgmin1": 949, "dmgrange": 0.6, "dmgtype1": 0, "dps": 521.73, "dura": 105, "hastertng": 110, "mledmgmax": 1764, "mledmgmin": 949, "mledps": 521.73, "mlespeed": 2.6, "reqlevel": 85, "sellprice": 342180, "sheathtype": 3, "slotbak": 13, "speed": 2.6, "sta": 248}, "68161": {"agi": 146, "appearances": {"0": [3447, ""]}, "displayid": 3447, "dmgmax1": 1563, "dmgmin1": 841, "dmgrange": 0.6, "dmgtype1": 0, "dps": 462.31, "dura": 105, "hastertng": 105, "hitrtng": 86, "mledmgmax": 1563, "mledmgmin": 841, "mledps": 462.31, "mlespeed": 2.6, "reqlevel": 85, "sellprice": 356170, "sheathtype": 3, "slotbak": 13, "speed": 2.6, "sta": 219}, "68600": {"agi": 165, "appearances": {"0": [71116, ""]}, "critstrkrtng": 110, "displayid": 71116, "dmgmax1": 950, "dmgmin1": 511, "dmgrange": 0.6, "dmgtype1": 0, "dps": 521.79, "dura": 75, "hastertng": 110, "mledmgmax": 950, "mledmgmin": 511, "mledps": 521.79, "mlespeed": 1.4, "reqlevel": 85, "sellprice": 351672, "sheathtype": 3, "slotbak": 13, "speed": 1.4, "sta": 248}, "65095": {"agi": 121, "appearances": {"0": [83162, ""]}, "critstrkrtng": 81, "displayid": 83162, "dmgmax1": 2533, "dmgmin1": 1688, "dmgrange": 0.4, "dmgtype1": 2, "dps": 703.5, "dura": 90, "hastertng": 81, "reqlevel": 85, "rgddmgmax": 2533, "rgddmgmin": 1688, "rgddps": 703.5, "rgdspeed": 3.0, "sellprice": 254742, "slotbak": 26, "speed": 3.0, "sta": 181}, "68608": {"agi": 107, "appearances": {"0": [65394, "inv_throwingaxepvp330_08"]}, "displayid": 65394, "dmgmax1": 1646, "dmgmin1": 1097, "dmgrange": 0.4, "dmgtype1": 0, "dps": 623.41, "hastertng": 72, "mastrtng": 72, "reqlevel": 85, "sellprice": 71245, "slotbak": 25, "speed": 2.2, "sta": 161}, "65077": {"appearances": {"0": [81960, ""]}, "armor": 1093, "critstrkrtng": 197, "displayid": 81960, "dura": 100, "int": 325, "mastrtng": 257, "nsockets": 2, "reqlevel": 85, "sellprice": 110546, "slotbak": 1, "socket1": 1, "socket2": 3, "socketbonus": 4138, "sta": 578}, "65138": {"appearances": {"0": [81951, ""]}, "armor": 589, "displayid": 81951, "dura": 55, "hastertng": 143, "int": 215, "mastrtng": 143, "reqlevel": 85, "sellprice": 68699, "slotbak": 9, "sta": 322}, "60247": {"appearances": {"0": [77130, ""]}, "armor": 782, "classes": 128, "critstrkrtng": 149, "displayid": 77130, "dura": 55, "int": 233, "itemset": 931, "mastrtng": 169, "nsockets": 1, "reqlevel": 85, "slotbak": 10, "socket1": 3, "socketbonus": 4123, "sta": 380}, "65256": {"appearances": {"0": [89762, ""]}, "armor": 2071, "classes": 64, "displayid": 89762, "dura": 100, "hastertng": 197, "int": 325, "itemset": -297, "mastrtng": 257, "nsockets": 2, "reqlevel": 85, "slotbak": 1, "socket1": 1, "socket2": 3, "socketbonus": 4150, "sta": 578}, "65112": {"hastertng": 143, "int": 215, "mastrtng": 143, "reqlevel": 85, "sellprice": 53434, "slotbak": 2, "sta": 322}, "60313": {"appearances": {"0": [82049, ""]}, "armor": 2433, "classes": 64, "critstrkrtng": 188, "displayid": 82049, "dura": 165, "hastertng": 228, "int": 301, "itemset": 940, "nsockets": 2, "reqlevel": 85, "slotbak": 5, "socket1": 2, "socket2": 4, "socketbonus": 4149, "sta": 512}, "65200": {"appearances": {"0": [93794, ""]}, "armor": 1439, "classes": 1024, "critstrkrtng": 257, "displayid": 93794, "dura": 100, "hastertng": 197, "int": 325, "itemset": -286, "nsockets": 2, "reqlevel": 85, "slotbak": 1, "socket1": 1, "socket2": 4, "socketbonus": 4150, "sta": 578}, "65045": {"appearances": {"0": [81709, ""]}, "armor": 1771, "displayid": 81709, "dmgrange": 0.2, "dura": 165, "int": 345, "mastrtng": 257, "nsockets": 2, "reqlevel": 85, "sellprice": 171729, "slotbak": 20, "socket1": 2, "socket2": 4, "socketbonus": 4137, "spi": 217, "sta": 578}, "65201": {"appearances": {"0": [81708, ""]}, "armor": 1550, "classes": 1024, "displayid": 81708, "dura": 120, "hastertng": 257, "int": 345, "itemset": -286, "nsockets": 2, "reqlevel": 85, "slotbak": 7, "socket1": 2, "socket2": 4, "socketbonus": 4144, "spi": 217, "sta": 578}, "65021": {"appearances": {"0": [81704, ""]}, "armor": 775, "displayid": 81704, "dura": 55, "int": 215, "mastrtng": 143, "reqlevel": 85, "sellprice": 84567, "slotbak": 9, "spi": 143, "sta": 322}, "60285": {"appearances": {"0": [76691, ""]}, "armor": 1043, "classes": 1024, "critstrkrtng": 169, "displayid": 76691, "dura": 55, "hastertng": 149, "int": 233, "itemset": 929, "nsockets": 1, "reqlevel": 85, "slotbak": 10, "socket1": 2, "socketbonus": 4151, "sta": 380}, "65213": {"appearances": {"0": [81959, ""]}, "armor": 1009, "classes": 128, "displayid": 81959, "dmgrange": 0.2, "dura": 100, "hastertng": 191, "hitrtng": 171, "int": 266, "itemset": -288, "nsockets": 1, "reqlevel": 85, "slotbak": 3, "socket1": 2, "socketbonus": 4146, "sta": 429}, "67133": {"appearances": {"0": [94248, ""]}, "armor": 1251, "critstrkrtng": 165, "displayid": 94248, "dura": 165, "int": 301, "mastrtng": 244, "nsockets": 2, "reqlevel": 85, "sellprice": 133277, "slotbak": 20, "socket1": 3, "socket2": 4, "socketbonus": 4144, "sta": 512}, "65211": {"appearances": {"0": [81958, ""]}, "armor": 1177, "classes": 128, "displayid": 81958, "dmgrange": 0.2, "dura": 120, "hastertng": 257, "hitrtng": 217, "int": 345, "itemset": -288, "nsockets": 2, "reqlevel": 85, "slotbak": 7, "socket1": 3, "socket2": 2, "socketbonus": 4144, "sta": 578}, "65266": {"appearances": {"0": [91566, ""]}, "armor": 2891, "classes": 1, "displayid": 91566, "dura": 100, "exprtng": 197, "hastertng": 257, "itemset": -299, "nsockets": 2, "reqlevel": 85, "slotbak": 1, "socket1": 1, "socket2": 3, "socketbonus": 4158, "sta": 578, "str": 325}, "65268": {"appearances": {"0": [91567, ""]}, "armor": 2669, "classes": 1, "displayid": 91567, "dura": 100, "hastertng": 191, "hitrtng": 171, "itemset": -299, "nsockets": 1, "reqlevel": 85, "slotbak": 3, "socket1": 2, "socketbonus": 4146, "sta": 429, "str": 266}, "65075": {"appearances": {"0": [82098, ""]}, "armor": 2447, "displayid": 82098, "dura": 75, "exprtng": 171, "mastrtng": 191, "nsockets": 1, "reqlevel": 85, "sellprice": 191727, "slotbak": 8, "socket1": 4, "socketbonus": 4135, "sta": 429, "str": 266}, "60226": {"critstrkrtng": 113, "mastrtng": 153, "nsockets": 1, "reqlevel": 85, "sellprice": 53434, "slotbak": 11, "socket1": 3, "socketbonus": 4135, "sta": 344, "str": 229}, "52222": {"avgbuyout": 1989994, "mlecritstrkrtng": 20, "rgdcritstrkrtng": 20, "sellprice": 37500, "splcritstrkrtng": 20, "str": 20, "color": 5}, "65117": {"appearances": {"0": [84196, ""]}, "armor": 673, "critstrkrtng": 143, "displayid": 84196, "hastertng": 143, "reqlevel": 85, "sellprice": 102664, "slotbak": 16, "sta": 322, "str": 215}, "65003": {"appearances": {"0": [71439, ""]}, "critstrkrtng": 257, "displayid": 71439, "dmgmax1": 3208, "dmgmin1": 2138, "dmgrange": 0.4, "dmgtype1": 0, "dps": 703.42, "dura": 120, "hitrtng": 257, "mledmgmax": 3208, "mledmgmin": 2138, "mledps": 703.42, "mlespeed": 3.8, "reqlevel": 85, "sellprice": 426169, "sheathtype": 1, "slotbak": 17, "speed": 3.8, "sta": 578, "str": 385}, "65238": {"appearances": {"0": [91290, ""]}, "armor": 1009, "classes": 16, "displayid": 91290, "dmgrange": 0.2, "dura": 100, "hastertng": 191, "int": 266, "itemset": -293, "nsockets": 1, "reqlevel": 85, "slotbak": 3, "socket1": 2, "socketbonus": 4146, "spi": 171, "sta": 429}, "65237": {"appearances": {"0": [92249, ""]}, "armor": 1346, "classes": 16, "critstrkrtng": 247, "displayid": 92249, "dura": 165, "hastertng": 227, "int": 345, "itemset": -293, "nsockets": 2, "reqlevel": 85, "slotbak": 20, "socket1": 2, "socket2": 4, "socketbonus": 4144, "sta": 578}, "54504": {"appearances": {"0": [82831, ""]}, "armor": 704, "avgbuyout": 90000084, "displayid": 82831, "dura": 55, "hastertng": 165, "int": 233, "nsockets": 1, "reqlevel": 85, "sellprice": 35819, "slotbak": 6, "socket1": 4, "socketbonus": 4143, "spi": 152, "sta": 380}, "65236": {"appearances": {"0": [82006, ""]}, "armor": 1177, "classes": 16, "displayid": 82006, "dmgrange": 0.2, "dura": 120, "hastertng": 257, "int": 345, "itemset": -293, "nsockets": 2, "reqlevel": 85, "slotbak": 7, "socket1": 3, "socket2": 2, "socketbonus": 4144, "spi": 217, "sta": 578}, "60238": {"appearances": {"0": [82004, ""]}, "armor": 612, "displayid": 82004, "dura": 55, "int": 209, "mastrtng": 153, "nsockets": 1, "reqlevel": 85, "sellprice": 73116, "slotbak": 9, "socket1": 3, "socketbonus": 4143, "spi": 133, "sta": 344}, "60339": {"appearances": {"0": [81303, ""]}, "armor": 3426, "classes": 32, "critstrkrtng": 228, "displayid": 81303, "dura": 165, "hastertng": 188, "itemset": 925, "nsockets": 2, "reqlevel": 85, "slotbak": 5, "socket1": 2, "socket2": 4, "socketbonus": 4136, "sta": 512, "str": 301}, "62430": {"appearances": {"0": [82126, ""]}, "armor": 2061, "buyprice": 429109, "critstrkrtng": 150, "displayid": 82126, "dura": 45, "hastertng": 130, "nsockets": 1, "reqfaction": 1174, "reqlevel": 85, "reqrep": 6, "sellprice": 85821, "slotbak": 10, "socket1": 3, "socketbonus": 4151, "sta": 337, "str": 205}, "56415": {"critstrkrtng": 112, "hitrtng": 112, "reqlevel": 85, "sellprice": 53434, "slotbak": 11, "sta": 252, "str": 168}, "65106": {"exprtng": 143, "hastertng": 143, "reqlevel": 85, "sellprice": 53434, "slotbak": 11, "sta": 322, "str": 215}, "56284": {"appearances": {"0": [77003, ""]}, "critstrkrtng": 216, "displayid": 77003, "dmgmax1": 2386, "dmgmin1": 1590, "dmgrange": 0.4, "dmgtype1": 0, "dps": 552.22, "dura": 100, "hastertng": 177, "mledmgmax": 2386, "mledmgmin": 1590, "mledps": 552.22, "mlespeed": 3.6, "reqlevel": 85, "sellprice": 306691, "sheathtype": 1, "slotbak": 17, "speed": 3.6, "sta": 454, "str": 302}, "65130": {"appearances": {"0": [90586, ""]}, "armor": 2891, "critstrkrtng": 197, "displayid": 90586, "dura": 100, "hastertng": 257, "nsockets": 2, "reqlevel": 85, "sellprice": 193162, "slotbak": 1, "socket1": 1, "socket2": 4, "socketbonus": 4128, "sta": 578, "str": 325}, "52176": {"avgbuyout": 1100218, "sellprice": 9000, "str": 35, "color": 0}, "60228": {"appearances": {"0": [78789, ""]}, "armor": 1589, "critstrkrtng": 153, "displayid": 78789, "dura": 55, "hastertng": 113, "nsockets": 1, "reqlevel": 85, "sellprice": 124009, "slotbak": 9, "socket1": 3, "socketbonus": 4135, "sta": 344, "str": 229}, "65180": {"appearances": {"0": [78787, ""]}, "armor": 2224, "classes": 32, "displayid": 78787, "dura": 55, "hastertng": 191, "itemset": -282, "mastrtng": 171, "nsockets": 1, "reqlevel": 85, "slotbak": 10, "socket1": 4, "socketbonus": 4135, "sta": 429, "str": 266}, "65171": {"appearances": {"0": [95620, ""]}, "displayid": 95620, "dmgmax1": 1491, "dmgmin1": 802, "dmgrange": 0.6, "dmgtype1": 0, "dps": 409.46, "dura": 90, "hitrtng": 86, "mastrtng": 86, "mledmgmax": 1491, "mledmgmin": 802, "mledps": 409.46, "mlespeed": 2.8, "reqlevel": 85, "sellprice": 258576, "sheathtype": 3, "slotbak": 13, "speed": 2.8, "sta": 194, "str": 129}, "65170": {"appearances": {"0": [7427, "inv_axe_01"]}, "displayid": 7427, "dmgmax1": 1384, "dmgmin1": 745, "dmgrange": 0.6, "dmgtype1": 0, "dps": 409.42, "dura": 90, "exprtng": 86, "hitrtng": 86, "mledmgmax": 1384, "mledmgmin": 745, "mledps": 409.42, "mlespeed": 2.6, "reqlevel": 85, "sellprice": 257656, "sheathtype": 3, "slotbak": 13, "speed": 2.6, "sta": 194, "str": 129}, "60243": {"appearances": {"0": [77144, ""]}, "armor": 1016, "classes": 128, "displayid": 77144, "dura": 100, "hastertng": 188, "int": 281, "itemset": 931, "mastrtng": 208, "nsockets": 2, "reqlevel": 85, "slotbak": 1, "socket1": 1, "socket2": 4, "socketbonus": 4153, "sta": 512}, "60246": {"appearances": {"0": [77134, ""]}, "armor": 938, "classes": 128, "displayid": 77134, "dmgrange": 0.2, "dura": 100, "hastertng": 169, "hitrtng": 149, "int": 233, "itemset": 931, "nsockets": 1, "reqlevel": 85, "slotbak": 3, "socket1": 2, "socketbonus": 4146, "sta": 380}, "65212": {"appearances": {"0": [93766, ""]}, "armor": 1346, "classes": 128, "critstrkrtng": 247, "displayid": 93766, "dura": 165, "hastertng": 227, "int": 345, "itemset": -288, "nsockets": 2, "reqlevel": 85, "slotbak": 20, "socket1": 2, "socket2": 4, "socketbonus": 4144, "sta": 578}, "52235": {"avgbuyout": 1000000, "mlehitrtng": 40, "rgdhitrtng": 40, "sellprice": 37500, "splhitrtng": 40, "color": 1}, "68127": {"appearances": {"0": [71114, ""]}, "displayid": 71114, "dmgmax1": 649.52001953125, "dmgmin1": 204.5199951171875, "dmgrange": 0.6, "dmgtype1": 0, "dps": 266.89, "dura": 105, "mledmgmax": 649.52001953125, "mledmgmin": 204.5199951171875, "mledps": 266.89, "mlespeed": 1.6, "reqlevel": 85, "sellprice": 329449, "sheathtype": 3, "slotbak": 21, "speed": 1.6, "spldmg": 1954, "splheal": 1954}, "63474": {"appearances": {"0": [87531, ""]}, "armor": 2061, "displayid": 87531, "dura": 45, "hastertng": 150, "mastrtng": 130, "nsockets": 1, "reqlevel": 85, "sellprice": 90380, "slotbak": 10, "socket1": 2, "socketbonus": 4211, "sta": 337, "str": 205}, "60347": {"appearances": {"0": [79841, ""]}, "armor": 2998, "classes": 2, "displayid": 79841, "dura": 120, "hitrtng": 188, "itemset": 932, "mastrtng": 228, "nsockets": 2, "reqlevel": 85, "slotbak": 7, "socket1": 3, "socket2": 3, "socketbonus": 4140, "sta": 512, "str": 301}, "65018": {"appearances": {"0": [79321, ""]}, "armor": 673, "critstrkrtng": 143, "displayid": 79321, "int": 215, "mastrtng": 143, "reqlevel": 85, "sellprice": 110983, "slotbak": 16, "sta": 322}, "56433": {"appearances": {"0": [76975, ""]}, "critstrkrtng": 93, "displayid": 76975, "dmgmax1": 852, "dmgmin1": 458, "dmgrange": 0.6, "dmgtype1": 0, "dps": 409.38, "dura": 90, "hastertng": 76, "int": 129, "mledmgmax": 852, "mledmgmin": 458, "mledps": 409.38, "mlespeed": 1.6, "reqlevel": 85, "sellprice": 248236, "sheathtype": 3, "slotbak": 21, "speed": 1.6, "spldmg": 1729, "splheal": 1729, "sta": 194}}